<?xml version="1.0" encoding="UTF-8"?>
<?xml-stylesheet href="CoreNLP-to-HTML.xsl" type="text/xsl"?>
<root>
  <document>
    <sentences>
      <sentence id="1">
        <tokens>
          <token id="1">
            <word>Captain</word>
            <lemma>Captain</lemma>
            <CharacterOffsetBegin>0</CharacterOffsetBegin>
            <CharacterOffsetEnd>7</CharacterOffsetEnd>
            <POS>NNP</POS>
            <NER>O</NER>
          </token>
          <token id="2">
            <word>Blood</word>
            <lemma>Blood</lemma>
            <CharacterOffsetBegin>8</CharacterOffsetBegin>
            <CharacterOffsetEnd>13</CharacterOffsetEnd>
            <POS>NNP</POS>
            <NER>O</NER>
          </token>
          <token id="3">
            <word>is</word>
            <lemma>be</lemma>
            <CharacterOffsetBegin>14</CharacterOffsetBegin>
            <CharacterOffsetEnd>16</CharacterOffsetEnd>
            <POS>VBZ</POS>
            <NER>O</NER>
          </token>
          <token id="4">
            <word>pardoned</word>
            <lemma>pardon</lemma>
            <CharacterOffsetBegin>17</CharacterOffsetBegin>
            <CharacterOffsetEnd>25</CharacterOffsetEnd>
            <POS>VBN</POS>
            <NER>O</NER>
          </token>
          <token id="5">
            <word>by</word>
            <lemma>by</lemma>
            <CharacterOffsetBegin>26</CharacterOffsetBegin>
            <CharacterOffsetEnd>28</CharacterOffsetEnd>
            <POS>IN</POS>
            <NER>O</NER>
          </token>
          <token id="6">
            <word>the</word>
            <lemma>the</lemma>
            <CharacterOffsetBegin>29</CharacterOffsetBegin>
            <CharacterOffsetEnd>32</CharacterOffsetEnd>
            <POS>DT</POS>
            <NER>O</NER>
          </token>
          <token id="7">
            <word>Crown</word>
            <lemma>Crown</lemma>
            <CharacterOffsetBegin>33</CharacterOffsetBegin>
            <CharacterOffsetEnd>38</CharacterOffsetEnd>
            <POS>NNP</POS>
            <NER>O</NER>
          </token>
          <token id="8">
            <word>for</word>
            <lemma>for</lemma>
            <CharacterOffsetBegin>39</CharacterOffsetBegin>
            <CharacterOffsetEnd>42</CharacterOffsetEnd>
            <POS>IN</POS>
            <NER>O</NER>
          </token>
          <token id="9">
            <word>his</word>
            <lemma>he</lemma>
            <CharacterOffsetBegin>43</CharacterOffsetBegin>
            <CharacterOffsetEnd>46</CharacterOffsetEnd>
            <POS>PRP$</POS>
            <NER>O</NER>
          </token>
          <token id="10">
            <word>crimes</word>
            <lemma>crime</lemma>
            <CharacterOffsetBegin>47</CharacterOffsetBegin>
            <CharacterOffsetEnd>53</CharacterOffsetEnd>
            <POS>NNS</POS>
            <NER>O</NER>
          </token>
          <token id="11">
            <word>against</word>
            <lemma>against</lemma>
            <CharacterOffsetBegin>54</CharacterOffsetBegin>
            <CharacterOffsetEnd>61</CharacterOffsetEnd>
            <POS>IN</POS>
            <NER>O</NER>
          </token>
          <token id="12">
            <word>Spain</word>
            <lemma>Spain</lemma>
            <CharacterOffsetBegin>62</CharacterOffsetBegin>
            <CharacterOffsetEnd>67</CharacterOffsetEnd>
            <POS>NNP</POS>
            <NER>LOCATION</NER>
          </token>
          <token id="13">
            <word>on</word>
            <lemma>on</lemma>
            <CharacterOffsetBegin>68</CharacterOffsetBegin>
            <CharacterOffsetEnd>70</CharacterOffsetEnd>
            <POS>IN</POS>
            <NER>O</NER>
          </token>
          <token id="14">
            <word>the</word>
            <lemma>the</lemma>
            <CharacterOffsetBegin>71</CharacterOffsetBegin>
            <CharacterOffsetEnd>74</CharacterOffsetEnd>
            <POS>DT</POS>
            <NER>O</NER>
          </token>
          <token id="15">
            <word>Spanish</word>
            <lemma>spanish</lemma>
            <CharacterOffsetBegin>75</CharacterOffsetBegin>
            <CharacterOffsetEnd>82</CharacterOffsetEnd>
            <POS>JJ</POS>
            <NER>MISC</NER>
          </token>
          <token id="16">
            <word>Main</word>
            <lemma>Main</lemma>
            <CharacterOffsetBegin>83</CharacterOffsetBegin>
            <CharacterOffsetEnd>87</CharacterOffsetEnd>
            <POS>NNP</POS>
            <NER>O</NER>
          </token>
          <token id="17">
            <word>.</word>
            <lemma>.</lemma>
            <CharacterOffsetBegin>87</CharacterOffsetBegin>
            <CharacterOffsetEnd>88</CharacterOffsetEnd>
            <POS>.</POS>
            <NER>O</NER>
          </token>
        </tokens>
        <parse>(ROOT (S (NP (NNP Captain) (NNP Blood)) (VP (VBZ is) (VP (VBN pardoned) (PP (IN by) (NP (NP (DT the) (NNP Crown)) (PP (IN for) (NP (PRP$ his) (NNS crimes))))) (PP (IN against) (NP (NNP Spain))) (PP (IN on) (NP (DT the) (JJ Spanish) (NNP Main))))) (. .))) </parse>
        <basic-dependencies>
          <dep type="nn">
            <governor idx="2">Blood</governor>
            <dependent idx="1">Captain</dependent>
          </dep>
          <dep type="nsubjpass">
            <governor idx="4">pardoned</governor>
            <dependent idx="2">Blood</dependent>
          </dep>
          <dep type="auxpass">
            <governor idx="4">pardoned</governor>
            <dependent idx="3">is</dependent>
          </dep>
          <dep type="prep">
            <governor idx="4">pardoned</governor>
            <dependent idx="5">by</dependent>
          </dep>
          <dep type="det">
            <governor idx="7">Crown</governor>
            <dependent idx="6">the</dependent>
          </dep>
          <dep type="pobj">
            <governor idx="5">by</governor>
            <dependent idx="7">Crown</dependent>
          </dep>
          <dep type="prep">
            <governor idx="7">Crown</governor>
            <dependent idx="8">for</dependent>
          </dep>
          <dep type="poss">
            <governor idx="10">crimes</governor>
            <dependent idx="9">his</dependent>
          </dep>
          <dep type="pobj">
            <governor idx="8">for</governor>
            <dependent idx="10">crimes</dependent>
          </dep>
          <dep type="prep">
            <governor idx="4">pardoned</governor>
            <dependent idx="11">against</dependent>
          </dep>
          <dep type="pobj">
            <governor idx="11">against</governor>
            <dependent idx="12">Spain</dependent>
          </dep>
          <dep type="prep">
            <governor idx="4">pardoned</governor>
            <dependent idx="13">on</dependent>
          </dep>
          <dep type="det">
            <governor idx="16">Main</governor>
            <dependent idx="14">the</dependent>
          </dep>
          <dep type="amod">
            <governor idx="16">Main</governor>
            <dependent idx="15">Spanish</dependent>
          </dep>
          <dep type="pobj">
            <governor idx="13">on</governor>
            <dependent idx="16">Main</dependent>
          </dep>
        </basic-dependencies>
        <collapsed-dependencies>
          <dep type="nn">
            <governor idx="2">Blood</governor>
            <dependent idx="1">Captain</dependent>
          </dep>
          <dep type="nsubjpass">
            <governor idx="4">pardoned</governor>
            <dependent idx="2">Blood</dependent>
          </dep>
          <dep type="auxpass">
            <governor idx="4">pardoned</governor>
            <dependent idx="3">is</dependent>
          </dep>
          <dep type="det">
            <governor idx="7">Crown</governor>
            <dependent idx="6">the</dependent>
          </dep>
          <dep type="agent">
            <governor idx="4">pardoned</governor>
            <dependent idx="7">Crown</dependent>
          </dep>
          <dep type="poss">
            <governor idx="10">crimes</governor>
            <dependent idx="9">his</dependent>
          </dep>
          <dep type="prep_for">
            <governor idx="7">Crown</governor>
            <dependent idx="10">crimes</dependent>
          </dep>
          <dep type="prep_against">
            <governor idx="4">pardoned</governor>
            <dependent idx="12">Spain</dependent>
          </dep>
          <dep type="det">
            <governor idx="16">Main</governor>
            <dependent idx="14">the</dependent>
          </dep>
          <dep type="amod">
            <governor idx="16">Main</governor>
            <dependent idx="15">Spanish</dependent>
          </dep>
          <dep type="prep_on">
            <governor idx="4">pardoned</governor>
            <dependent idx="16">Main</dependent>
          </dep>
        </collapsed-dependencies>
        <collapsed-ccprocessed-dependencies>
          <dep type="nn">
            <governor idx="2">Blood</governor>
            <dependent idx="1">Captain</dependent>
          </dep>
          <dep type="nsubjpass">
            <governor idx="4">pardoned</governor>
            <dependent idx="2">Blood</dependent>
          </dep>
          <dep type="auxpass">
            <governor idx="4">pardoned</governor>
            <dependent idx="3">is</dependent>
          </dep>
          <dep type="det">
            <governor idx="7">Crown</governor>
            <dependent idx="6">the</dependent>
          </dep>
          <dep type="agent">
            <governor idx="4">pardoned</governor>
            <dependent idx="7">Crown</dependent>
          </dep>
          <dep type="poss">
            <governor idx="10">crimes</governor>
            <dependent idx="9">his</dependent>
          </dep>
          <dep type="prep_for">
            <governor idx="7">Crown</governor>
            <dependent idx="10">crimes</dependent>
          </dep>
          <dep type="prep_against">
            <governor idx="4">pardoned</governor>
            <dependent idx="12">Spain</dependent>
          </dep>
          <dep type="det">
            <governor idx="16">Main</governor>
            <dependent idx="14">the</dependent>
          </dep>
          <dep type="amod">
            <governor idx="16">Main</governor>
            <dependent idx="15">Spanish</dependent>
          </dep>
          <dep type="prep_on">
            <governor idx="4">pardoned</governor>
            <dependent idx="16">Main</dependent>
          </dep>
        </collapsed-ccprocessed-dependencies>
      </sentence>
      <sentence id="2">
        <tokens>
          <token id="1">
            <word>By</word>
            <lemma>by</lemma>
            <CharacterOffsetBegin>89</CharacterOffsetBegin>
            <CharacterOffsetEnd>91</CharacterOffsetEnd>
            <POS>IN</POS>
            <NER>O</NER>
          </token>
          <token id="2">
            <word>1690</word>
            <lemma>1690</lemma>
            <CharacterOffsetBegin>92</CharacterOffsetBegin>
            <CharacterOffsetEnd>96</CharacterOffsetEnd>
            <POS>CD</POS>
            <NER>DATE</NER>
            <NormalizedNER>1690</NormalizedNER>
            <Timex tid="t1" type="DATE">1690</Timex>
          </token>
          <token id="3">
            <word>he</word>
            <lemma>he</lemma>
            <CharacterOffsetBegin>97</CharacterOffsetBegin>
            <CharacterOffsetEnd>99</CharacterOffsetEnd>
            <POS>PRP</POS>
            <NER>O</NER>
          </token>
          <token id="4">
            <word>is</word>
            <lemma>be</lemma>
            <CharacterOffsetBegin>100</CharacterOffsetBegin>
            <CharacterOffsetEnd>102</CharacterOffsetEnd>
            <POS>VBZ</POS>
            <NER>O</NER>
          </token>
          <token id="5">
            <word>living</word>
            <lemma>live</lemma>
            <CharacterOffsetBegin>103</CharacterOffsetBegin>
            <CharacterOffsetEnd>109</CharacterOffsetEnd>
            <POS>VBG</POS>
            <NER>O</NER>
          </token>
          <token id="6">
            <word>in</word>
            <lemma>in</lemma>
            <CharacterOffsetBegin>110</CharacterOffsetBegin>
            <CharacterOffsetEnd>112</CharacterOffsetEnd>
            <POS>IN</POS>
            <NER>O</NER>
          </token>
          <token id="7">
            <word>the</word>
            <lemma>the</lemma>
            <CharacterOffsetBegin>113</CharacterOffsetBegin>
            <CharacterOffsetEnd>116</CharacterOffsetEnd>
            <POS>DT</POS>
            <NER>O</NER>
          </token>
          <token id="8">
            <word>West</word>
            <lemma>West</lemma>
            <CharacterOffsetBegin>117</CharacterOffsetBegin>
            <CharacterOffsetEnd>121</CharacterOffsetEnd>
            <POS>NNP</POS>
            <NER>LOCATION</NER>
          </token>
          <token id="9">
            <word>Indies</word>
            <lemma>Indies</lemma>
            <CharacterOffsetBegin>122</CharacterOffsetBegin>
            <CharacterOffsetEnd>128</CharacterOffsetEnd>
            <POS>NNP</POS>
            <NER>LOCATION</NER>
          </token>
          <token id="10">
            <word>on</word>
            <lemma>on</lemma>
            <CharacterOffsetBegin>129</CharacterOffsetBegin>
            <CharacterOffsetEnd>131</CharacterOffsetEnd>
            <POS>IN</POS>
            <NER>O</NER>
          </token>
          <token id="11">
            <word>his</word>
            <lemma>he</lemma>
            <CharacterOffsetBegin>132</CharacterOffsetBegin>
            <CharacterOffsetEnd>135</CharacterOffsetEnd>
            <POS>PRP$</POS>
            <NER>O</NER>
          </token>
          <token id="12">
            <word>plantation</word>
            <lemma>plantation</lemma>
            <CharacterOffsetBegin>136</CharacterOffsetBegin>
            <CharacterOffsetEnd>146</CharacterOffsetEnd>
            <POS>NN</POS>
            <NER>O</NER>
          </token>
          <token id="13">
            <word>where</word>
            <lemma>where</lemma>
            <CharacterOffsetBegin>147</CharacterOffsetBegin>
            <CharacterOffsetEnd>152</CharacterOffsetEnd>
            <POS>WRB</POS>
            <NER>O</NER>
          </token>
          <token id="14">
            <word>he</word>
            <lemma>he</lemma>
            <CharacterOffsetBegin>153</CharacterOffsetBegin>
            <CharacterOffsetEnd>155</CharacterOffsetEnd>
            <POS>PRP</POS>
            <NER>O</NER>
          </token>
          <token id="15">
            <word>practices</word>
            <lemma>practice</lemma>
            <CharacterOffsetBegin>156</CharacterOffsetBegin>
            <CharacterOffsetEnd>165</CharacterOffsetEnd>
            <POS>NNS</POS>
            <NER>O</NER>
          </token>
          <token id="16">
            <word>medicine</word>
            <lemma>medicine</lemma>
            <CharacterOffsetBegin>166</CharacterOffsetBegin>
            <CharacterOffsetEnd>174</CharacterOffsetEnd>
            <POS>NN</POS>
            <NER>O</NER>
          </token>
          <token id="17">
            <word>and</word>
            <lemma>and</lemma>
            <CharacterOffsetBegin>175</CharacterOffsetBegin>
            <CharacterOffsetEnd>178</CharacterOffsetEnd>
            <POS>CC</POS>
            <NER>O</NER>
          </token>
          <token id="18">
            <word>is</word>
            <lemma>be</lemma>
            <CharacterOffsetBegin>179</CharacterOffsetBegin>
            <CharacterOffsetEnd>181</CharacterOffsetEnd>
            <POS>VBZ</POS>
            <NER>O</NER>
          </token>
          <token id="19">
            <word>to</word>
            <lemma>to</lemma>
            <CharacterOffsetBegin>182</CharacterOffsetBegin>
            <CharacterOffsetEnd>184</CharacterOffsetEnd>
            <POS>TO</POS>
            <NER>O</NER>
          </token>
          <token id="20">
            <word>be</word>
            <lemma>be</lemma>
            <CharacterOffsetBegin>185</CharacterOffsetBegin>
            <CharacterOffsetEnd>187</CharacterOffsetEnd>
            <POS>VB</POS>
            <NER>O</NER>
          </token>
          <token id="21">
            <word>married</word>
            <lemma>marry</lemma>
            <CharacterOffsetBegin>188</CharacterOffsetBegin>
            <CharacterOffsetEnd>195</CharacterOffsetEnd>
            <POS>VBN</POS>
            <NER>O</NER>
          </token>
          <token id="22">
            <word>to</word>
            <lemma>to</lemma>
            <CharacterOffsetBegin>196</CharacterOffsetBegin>
            <CharacterOffsetEnd>198</CharacterOffsetEnd>
            <POS>TO</POS>
            <NER>O</NER>
          </token>
          <token id="23">
            <word>Isabella</word>
            <lemma>Isabella</lemma>
            <CharacterOffsetBegin>199</CharacterOffsetBegin>
            <CharacterOffsetEnd>207</CharacterOffsetEnd>
            <POS>NNP</POS>
            <NER>PERSON</NER>
          </token>
          <token id="24">
            <word>.</word>
            <lemma>.</lemma>
            <CharacterOffsetBegin>207</CharacterOffsetBegin>
            <CharacterOffsetEnd>208</CharacterOffsetEnd>
            <POS>.</POS>
            <NER>O</NER>
          </token>
        </tokens>
        <parse>(ROOT (S (PP (IN By) (NP (CD 1690))) (NP (PRP he)) (VP (VP (VBZ is) (VP (VBG living) (PP (IN in) (NP (NP (DT the) (NNP West) (NNP Indies)) (PP (IN on) (NP (PRP$ his) (NN plantation))) (SBAR (WHADVP (WRB where)) (S (NP (PRP he)) (NP (NNS practices) (NN medicine)))))))) (CC and) (VP (VBZ is) (S (VP (TO to) (VP (VB be) (VP (VBN married) (PP (TO to) (NP (NNP Isabella))))))))) (. .))) </parse>
        <basic-dependencies>
          <dep type="prep">
            <governor idx="5">living</governor>
            <dependent idx="1">By</dependent>
          </dep>
          <dep type="pobj">
            <governor idx="1">By</governor>
            <dependent idx="2">1690</dependent>
          </dep>
          <dep type="nsubj">
            <governor idx="5">living</governor>
            <dependent idx="3">he</dependent>
          </dep>
          <dep type="aux">
            <governor idx="5">living</governor>
            <dependent idx="4">is</dependent>
          </dep>
          <dep type="prep">
            <governor idx="5">living</governor>
            <dependent idx="6">in</dependent>
          </dep>
          <dep type="det">
            <governor idx="9">Indies</governor>
            <dependent idx="7">the</dependent>
          </dep>
          <dep type="nn">
            <governor idx="9">Indies</governor>
            <dependent idx="8">West</dependent>
          </dep>
          <dep type="pobj">
            <governor idx="6">in</governor>
            <dependent idx="9">Indies</dependent>
          </dep>
          <dep type="prep">
            <governor idx="9">Indies</governor>
            <dependent idx="10">on</dependent>
          </dep>
          <dep type="poss">
            <governor idx="12">plantation</governor>
            <dependent idx="11">his</dependent>
          </dep>
          <dep type="pobj">
            <governor idx="10">on</governor>
            <dependent idx="12">plantation</dependent>
          </dep>
          <dep type="advmod">
            <governor idx="16">medicine</governor>
            <dependent idx="13">where</dependent>
          </dep>
          <dep type="dep">
            <governor idx="16">medicine</governor>
            <dependent idx="14">he</dependent>
          </dep>
          <dep type="nn">
            <governor idx="16">medicine</governor>
            <dependent idx="15">practices</dependent>
          </dep>
          <dep type="rcmod">
            <governor idx="9">Indies</governor>
            <dependent idx="16">medicine</dependent>
          </dep>
          <dep type="cc">
            <governor idx="5">living</governor>
            <dependent idx="17">and</dependent>
          </dep>
          <dep type="conj">
            <governor idx="5">living</governor>
            <dependent idx="18">is</dependent>
          </dep>
          <dep type="aux">
            <governor idx="21">married</governor>
            <dependent idx="19">to</dependent>
          </dep>
          <dep type="auxpass">
            <governor idx="21">married</governor>
            <dependent idx="20">be</dependent>
          </dep>
          <dep type="xcomp">
            <governor idx="18">is</governor>
            <dependent idx="21">married</dependent>
          </dep>
          <dep type="prep">
            <governor idx="21">married</governor>
            <dependent idx="22">to</dependent>
          </dep>
          <dep type="pobj">
            <governor idx="22">to</governor>
            <dependent idx="23">Isabella</dependent>
          </dep>
        </basic-dependencies>
        <collapsed-dependencies>
          <dep type="prep_by">
            <governor idx="5">living</governor>
            <dependent idx="2">1690</dependent>
          </dep>
          <dep type="nsubj">
            <governor idx="5">living</governor>
            <dependent idx="3">he</dependent>
          </dep>
          <dep type="aux">
            <governor idx="5">living</governor>
            <dependent idx="4">is</dependent>
          </dep>
          <dep type="det">
            <governor idx="9">Indies</governor>
            <dependent idx="7">the</dependent>
          </dep>
          <dep type="nn">
            <governor idx="9">Indies</governor>
            <dependent idx="8">West</dependent>
          </dep>
          <dep type="prep_in">
            <governor idx="5">living</governor>
            <dependent idx="9">Indies</dependent>
          </dep>
          <dep type="poss">
            <governor idx="12">plantation</governor>
            <dependent idx="11">his</dependent>
          </dep>
          <dep type="prep_on">
            <governor idx="9">Indies</governor>
            <dependent idx="12">plantation</dependent>
          </dep>
          <dep type="advmod">
            <governor idx="16">medicine</governor>
            <dependent idx="13">where</dependent>
          </dep>
          <dep type="dep">
            <governor idx="16">medicine</governor>
            <dependent idx="14">he</dependent>
          </dep>
          <dep type="nn">
            <governor idx="16">medicine</governor>
            <dependent idx="15">practices</dependent>
          </dep>
          <dep type="rcmod">
            <governor idx="9">Indies</governor>
            <dependent idx="16">medicine</dependent>
          </dep>
          <dep type="conj_and">
            <governor idx="5">living</governor>
            <dependent idx="18">is</dependent>
          </dep>
          <dep type="aux">
            <governor idx="21">married</governor>
            <dependent idx="19">to</dependent>
          </dep>
          <dep type="auxpass">
            <governor idx="21">married</governor>
            <dependent idx="20">be</dependent>
          </dep>
          <dep type="xcomp">
            <governor idx="18">is</governor>
            <dependent idx="21">married</dependent>
          </dep>
          <dep type="prep_to">
            <governor idx="21">married</governor>
            <dependent idx="23">Isabella</dependent>
          </dep>
        </collapsed-dependencies>
        <collapsed-ccprocessed-dependencies>
          <dep type="prep_by">
            <governor idx="5">living</governor>
            <dependent idx="2">1690</dependent>
          </dep>
          <dep type="nsubj">
            <governor idx="5">living</governor>
            <dependent idx="3">he</dependent>
          </dep>
          <dep type="nsubj">
            <governor idx="18">is</governor>
            <dependent idx="3">he</dependent>
          </dep>
          <dep type="aux">
            <governor idx="5">living</governor>
            <dependent idx="4">is</dependent>
          </dep>
          <dep type="det">
            <governor idx="9">Indies</governor>
            <dependent idx="7">the</dependent>
          </dep>
          <dep type="nn">
            <governor idx="9">Indies</governor>
            <dependent idx="8">West</dependent>
          </dep>
          <dep type="prep_in">
            <governor idx="5">living</governor>
            <dependent idx="9">Indies</dependent>
          </dep>
          <dep type="poss">
            <governor idx="12">plantation</governor>
            <dependent idx="11">his</dependent>
          </dep>
          <dep type="prep_on">
            <governor idx="9">Indies</governor>
            <dependent idx="12">plantation</dependent>
          </dep>
          <dep type="advmod">
            <governor idx="16">medicine</governor>
            <dependent idx="13">where</dependent>
          </dep>
          <dep type="dep">
            <governor idx="16">medicine</governor>
            <dependent idx="14">he</dependent>
          </dep>
          <dep type="nn">
            <governor idx="16">medicine</governor>
            <dependent idx="15">practices</dependent>
          </dep>
          <dep type="rcmod">
            <governor idx="9">Indies</governor>
            <dependent idx="16">medicine</dependent>
          </dep>
          <dep type="conj_and">
            <governor idx="5">living</governor>
            <dependent idx="18">is</dependent>
          </dep>
          <dep type="aux">
            <governor idx="21">married</governor>
            <dependent idx="19">to</dependent>
          </dep>
          <dep type="auxpass">
            <governor idx="21">married</governor>
            <dependent idx="20">be</dependent>
          </dep>
          <dep type="xcomp">
            <governor idx="18">is</governor>
            <dependent idx="21">married</dependent>
          </dep>
          <dep type="prep_to">
            <governor idx="21">married</governor>
            <dependent idx="23">Isabella</dependent>
          </dep>
        </collapsed-ccprocessed-dependencies>
      </sentence>
      <sentence id="3">
        <tokens>
          <token id="1">
            <word>His</word>
            <lemma>he</lemma>
            <CharacterOffsetBegin>209</CharacterOffsetBegin>
            <CharacterOffsetEnd>212</CharacterOffsetEnd>
            <POS>PRP$</POS>
            <NER>O</NER>
          </token>
          <token id="2">
            <word>new</word>
            <lemma>new</lemma>
            <CharacterOffsetBegin>213</CharacterOffsetBegin>
            <CharacterOffsetEnd>216</CharacterOffsetEnd>
            <POS>JJ</POS>
            <NER>O</NER>
          </token>
          <token id="3">
            <word>life</word>
            <lemma>life</lemma>
            <CharacterOffsetBegin>217</CharacterOffsetBegin>
            <CharacterOffsetEnd>221</CharacterOffsetEnd>
            <POS>NN</POS>
            <NER>O</NER>
          </token>
          <token id="4">
            <word>is</word>
            <lemma>be</lemma>
            <CharacterOffsetBegin>222</CharacterOffsetBegin>
            <CharacterOffsetEnd>224</CharacterOffsetEnd>
            <POS>VBZ</POS>
            <NER>O</NER>
          </token>
          <token id="5">
            <word>put</word>
            <lemma>put</lemma>
            <CharacterOffsetBegin>225</CharacterOffsetBegin>
            <CharacterOffsetEnd>228</CharacterOffsetEnd>
            <POS>VBN</POS>
            <NER>O</NER>
          </token>
          <token id="6">
            <word>in</word>
            <lemma>in</lemma>
            <CharacterOffsetBegin>229</CharacterOffsetBegin>
            <CharacterOffsetEnd>231</CharacterOffsetEnd>
            <POS>IN</POS>
            <NER>O</NER>
          </token>
          <token id="7">
            <word>danger</word>
            <lemma>danger</lemma>
            <CharacterOffsetBegin>232</CharacterOffsetBegin>
            <CharacterOffsetEnd>238</CharacterOffsetEnd>
            <POS>NN</POS>
            <NER>O</NER>
          </token>
          <token id="8">
            <word>when</word>
            <lemma>when</lemma>
            <CharacterOffsetBegin>239</CharacterOffsetBegin>
            <CharacterOffsetEnd>243</CharacterOffsetEnd>
            <POS>WRB</POS>
            <NER>O</NER>
          </token>
          <token id="9">
            <word>he</word>
            <lemma>he</lemma>
            <CharacterOffsetBegin>244</CharacterOffsetBegin>
            <CharacterOffsetEnd>246</CharacterOffsetEnd>
            <POS>PRP</POS>
            <NER>O</NER>
          </token>
          <token id="10">
            <word>is</word>
            <lemma>be</lemma>
            <CharacterOffsetBegin>247</CharacterOffsetBegin>
            <CharacterOffsetEnd>249</CharacterOffsetEnd>
            <POS>VBZ</POS>
            <NER>O</NER>
          </token>
          <token id="11">
            <word>arrested</word>
            <lemma>arrest</lemma>
            <CharacterOffsetBegin>250</CharacterOffsetBegin>
            <CharacterOffsetEnd>258</CharacterOffsetEnd>
            <POS>VBN</POS>
            <NER>O</NER>
          </token>
          <token id="12">
            <word>on</word>
            <lemma>on</lemma>
            <CharacterOffsetBegin>259</CharacterOffsetBegin>
            <CharacterOffsetEnd>261</CharacterOffsetEnd>
            <POS>IN</POS>
            <NER>O</NER>
          </token>
          <token id="13">
            <word>a</word>
            <lemma>a</lemma>
            <CharacterOffsetBegin>262</CharacterOffsetBegin>
            <CharacterOffsetEnd>263</CharacterOffsetEnd>
            <POS>DT</POS>
            <NER>O</NER>
          </token>
          <token id="14">
            <word>piracy</word>
            <lemma>piracy</lemma>
            <CharacterOffsetBegin>264</CharacterOffsetBegin>
            <CharacterOffsetEnd>270</CharacterOffsetEnd>
            <POS>NN</POS>
            <NER>O</NER>
          </token>
          <token id="15">
            <word>charge</word>
            <lemma>charge</lemma>
            <CharacterOffsetBegin>271</CharacterOffsetBegin>
            <CharacterOffsetEnd>277</CharacterOffsetEnd>
            <POS>NN</POS>
            <NER>O</NER>
          </token>
          <token id="16">
            <word>after</word>
            <lemma>after</lemma>
            <CharacterOffsetBegin>278</CharacterOffsetBegin>
            <CharacterOffsetEnd>283</CharacterOffsetEnd>
            <POS>IN</POS>
            <NER>O</NER>
          </token>
          <token id="17">
            <word>somebody</word>
            <lemma>somebody</lemma>
            <CharacterOffsetBegin>284</CharacterOffsetBegin>
            <CharacterOffsetEnd>292</CharacterOffsetEnd>
            <POS>NN</POS>
            <NER>O</NER>
          </token>
          <token id="18">
            <word>raids</word>
            <lemma>raid</lemma>
            <CharacterOffsetBegin>293</CharacterOffsetBegin>
            <CharacterOffsetEnd>298</CharacterOffsetEnd>
            <POS>VBZ</POS>
            <NER>O</NER>
          </token>
          <token id="19">
            <word>the</word>
            <lemma>the</lemma>
            <CharacterOffsetBegin>299</CharacterOffsetBegin>
            <CharacterOffsetEnd>302</CharacterOffsetEnd>
            <POS>DT</POS>
            <NER>O</NER>
          </token>
          <token id="20">
            <word>island</word>
            <lemma>island</lemma>
            <CharacterOffsetBegin>303</CharacterOffsetBegin>
            <CharacterOffsetEnd>309</CharacterOffsetEnd>
            <POS>NN</POS>
            <NER>O</NER>
          </token>
          <token id="21">
            <word>making</word>
            <lemma>make</lemma>
            <CharacterOffsetBegin>310</CharacterOffsetBegin>
            <CharacterOffsetEnd>316</CharacterOffsetEnd>
            <POS>VBG</POS>
            <NER>O</NER>
          </token>
          <token id="22">
            <word>him</word>
            <lemma>he</lemma>
            <CharacterOffsetBegin>317</CharacterOffsetBegin>
            <CharacterOffsetEnd>320</CharacterOffsetEnd>
            <POS>PRP</POS>
            <NER>O</NER>
          </token>
          <token id="23">
            <word>look</word>
            <lemma>look</lemma>
            <CharacterOffsetBegin>321</CharacterOffsetBegin>
            <CharacterOffsetEnd>325</CharacterOffsetEnd>
            <POS>VB</POS>
            <NER>O</NER>
          </token>
          <token id="24">
            <word>guilty</word>
            <lemma>guilty</lemma>
            <CharacterOffsetBegin>326</CharacterOffsetBegin>
            <CharacterOffsetEnd>332</CharacterOffsetEnd>
            <POS>JJ</POS>
            <NER>O</NER>
          </token>
          <token id="25">
            <word>.</word>
            <lemma>.</lemma>
            <CharacterOffsetBegin>332</CharacterOffsetBegin>
            <CharacterOffsetEnd>333</CharacterOffsetEnd>
            <POS>.</POS>
            <NER>O</NER>
          </token>
        </tokens>
        <parse>(ROOT (S (NP (PRP$ His) (JJ new) (NN life)) (VP (VBZ is) (VP (VBN put) (PP (IN in) (NP (NN danger))) (SBAR (WHADVP (WRB when)) (S (NP (PRP he)) (VP (VBZ is) (VP (VBN arrested) (PP (IN on) (NP (DT a) (NN piracy) (NN charge))) (SBAR (IN after) (S (NP (NN somebody)) (VP (VBZ raids) (NP (NP (DT the) (NN island)) (VP (VBG making) (S (NP (PRP him)) (VP (VB look) (ADJP (JJ guilty))))))))))))))) (. .))) </parse>
        <basic-dependencies>
          <dep type="poss">
            <governor idx="3">life</governor>
            <dependent idx="1">His</dependent>
          </dep>
          <dep type="amod">
            <governor idx="3">life</governor>
            <dependent idx="2">new</dependent>
          </dep>
          <dep type="nsubjpass">
            <governor idx="5">put</governor>
            <dependent idx="3">life</dependent>
          </dep>
          <dep type="auxpass">
            <governor idx="5">put</governor>
            <dependent idx="4">is</dependent>
          </dep>
          <dep type="prep">
            <governor idx="5">put</governor>
            <dependent idx="6">in</dependent>
          </dep>
          <dep type="pobj">
            <governor idx="6">in</governor>
            <dependent idx="7">danger</dependent>
          </dep>
          <dep type="advmod">
            <governor idx="11">arrested</governor>
            <dependent idx="8">when</dependent>
          </dep>
          <dep type="nsubjpass">
            <governor idx="11">arrested</governor>
            <dependent idx="9">he</dependent>
          </dep>
          <dep type="auxpass">
            <governor idx="11">arrested</governor>
            <dependent idx="10">is</dependent>
          </dep>
          <dep type="advcl">
            <governor idx="5">put</governor>
            <dependent idx="11">arrested</dependent>
          </dep>
          <dep type="prep">
            <governor idx="11">arrested</governor>
            <dependent idx="12">on</dependent>
          </dep>
          <dep type="det">
            <governor idx="15">charge</governor>
            <dependent idx="13">a</dependent>
          </dep>
          <dep type="nn">
            <governor idx="15">charge</governor>
            <dependent idx="14">piracy</dependent>
          </dep>
          <dep type="pobj">
            <governor idx="12">on</governor>
            <dependent idx="15">charge</dependent>
          </dep>
          <dep type="mark">
            <governor idx="18">raids</governor>
            <dependent idx="16">after</dependent>
          </dep>
          <dep type="nsubj">
            <governor idx="18">raids</governor>
            <dependent idx="17">somebody</dependent>
          </dep>
          <dep type="advcl">
            <governor idx="11">arrested</governor>
            <dependent idx="18">raids</dependent>
          </dep>
          <dep type="det">
            <governor idx="20">island</governor>
            <dependent idx="19">the</dependent>
          </dep>
          <dep type="dobj">
            <governor idx="18">raids</governor>
            <dependent idx="20">island</dependent>
          </dep>
          <dep type="partmod">
            <governor idx="20">island</governor>
            <dependent idx="21">making</dependent>
          </dep>
          <dep type="nsubj">
            <governor idx="23">look</governor>
            <dependent idx="22">him</dependent>
          </dep>
          <dep type="ccomp">
            <governor idx="21">making</governor>
            <dependent idx="23">look</dependent>
          </dep>
          <dep type="acomp">
            <governor idx="23">look</governor>
            <dependent idx="24">guilty</dependent>
          </dep>
        </basic-dependencies>
        <collapsed-dependencies>
          <dep type="poss">
            <governor idx="3">life</governor>
            <dependent idx="1">His</dependent>
          </dep>
          <dep type="amod">
            <governor idx="3">life</governor>
            <dependent idx="2">new</dependent>
          </dep>
          <dep type="nsubjpass">
            <governor idx="5">put</governor>
            <dependent idx="3">life</dependent>
          </dep>
          <dep type="auxpass">
            <governor idx="5">put</governor>
            <dependent idx="4">is</dependent>
          </dep>
          <dep type="prep_in">
            <governor idx="5">put</governor>
            <dependent idx="7">danger</dependent>
          </dep>
          <dep type="advmod">
            <governor idx="11">arrested</governor>
            <dependent idx="8">when</dependent>
          </dep>
          <dep type="nsubjpass">
            <governor idx="11">arrested</governor>
            <dependent idx="9">he</dependent>
          </dep>
          <dep type="auxpass">
            <governor idx="11">arrested</governor>
            <dependent idx="10">is</dependent>
          </dep>
          <dep type="advcl">
            <governor idx="5">put</governor>
            <dependent idx="11">arrested</dependent>
          </dep>
          <dep type="det">
            <governor idx="15">charge</governor>
            <dependent idx="13">a</dependent>
          </dep>
          <dep type="nn">
            <governor idx="15">charge</governor>
            <dependent idx="14">piracy</dependent>
          </dep>
          <dep type="prep_on">
            <governor idx="11">arrested</governor>
            <dependent idx="15">charge</dependent>
          </dep>
          <dep type="mark">
            <governor idx="18">raids</governor>
            <dependent idx="16">after</dependent>
          </dep>
          <dep type="nsubj">
            <governor idx="18">raids</governor>
            <dependent idx="17">somebody</dependent>
          </dep>
          <dep type="advcl">
            <governor idx="11">arrested</governor>
            <dependent idx="18">raids</dependent>
          </dep>
          <dep type="det">
            <governor idx="20">island</governor>
            <dependent idx="19">the</dependent>
          </dep>
          <dep type="dobj">
            <governor idx="18">raids</governor>
            <dependent idx="20">island</dependent>
          </dep>
          <dep type="partmod">
            <governor idx="20">island</governor>
            <dependent idx="21">making</dependent>
          </dep>
          <dep type="nsubj">
            <governor idx="23">look</governor>
            <dependent idx="22">him</dependent>
          </dep>
          <dep type="ccomp">
            <governor idx="21">making</governor>
            <dependent idx="23">look</dependent>
          </dep>
          <dep type="acomp">
            <governor idx="23">look</governor>
            <dependent idx="24">guilty</dependent>
          </dep>
        </collapsed-dependencies>
        <collapsed-ccprocessed-dependencies>
          <dep type="poss">
            <governor idx="3">life</governor>
            <dependent idx="1">His</dependent>
          </dep>
          <dep type="amod">
            <governor idx="3">life</governor>
            <dependent idx="2">new</dependent>
          </dep>
          <dep type="nsubjpass">
            <governor idx="5">put</governor>
            <dependent idx="3">life</dependent>
          </dep>
          <dep type="auxpass">
            <governor idx="5">put</governor>
            <dependent idx="4">is</dependent>
          </dep>
          <dep type="prep_in">
            <governor idx="5">put</governor>
            <dependent idx="7">danger</dependent>
          </dep>
          <dep type="advmod">
            <governor idx="11">arrested</governor>
            <dependent idx="8">when</dependent>
          </dep>
          <dep type="nsubjpass">
            <governor idx="11">arrested</governor>
            <dependent idx="9">he</dependent>
          </dep>
          <dep type="auxpass">
            <governor idx="11">arrested</governor>
            <dependent idx="10">is</dependent>
          </dep>
          <dep type="advcl">
            <governor idx="5">put</governor>
            <dependent idx="11">arrested</dependent>
          </dep>
          <dep type="det">
            <governor idx="15">charge</governor>
            <dependent idx="13">a</dependent>
          </dep>
          <dep type="nn">
            <governor idx="15">charge</governor>
            <dependent idx="14">piracy</dependent>
          </dep>
          <dep type="prep_on">
            <governor idx="11">arrested</governor>
            <dependent idx="15">charge</dependent>
          </dep>
          <dep type="mark">
            <governor idx="18">raids</governor>
            <dependent idx="16">after</dependent>
          </dep>
          <dep type="nsubj">
            <governor idx="18">raids</governor>
            <dependent idx="17">somebody</dependent>
          </dep>
          <dep type="advcl">
            <governor idx="11">arrested</governor>
            <dependent idx="18">raids</dependent>
          </dep>
          <dep type="det">
            <governor idx="20">island</governor>
            <dependent idx="19">the</dependent>
          </dep>
          <dep type="dobj">
            <governor idx="18">raids</governor>
            <dependent idx="20">island</dependent>
          </dep>
          <dep type="partmod">
            <governor idx="20">island</governor>
            <dependent idx="21">making</dependent>
          </dep>
          <dep type="nsubj">
            <governor idx="23">look</governor>
            <dependent idx="22">him</dependent>
          </dep>
          <dep type="ccomp">
            <governor idx="21">making</governor>
            <dependent idx="23">look</dependent>
          </dep>
          <dep type="acomp">
            <governor idx="23">look</governor>
            <dependent idx="24">guilty</dependent>
          </dep>
        </collapsed-ccprocessed-dependencies>
      </sentence>
      <sentence id="4">
        <tokens>
          <token id="1">
            <word>To</word>
            <lemma>to</lemma>
            <CharacterOffsetBegin>334</CharacterOffsetBegin>
            <CharacterOffsetEnd>336</CharacterOffsetEnd>
            <POS>TO</POS>
            <NER>O</NER>
          </token>
          <token id="2">
            <word>prove</word>
            <lemma>prove</lemma>
            <CharacterOffsetBegin>337</CharacterOffsetBegin>
            <CharacterOffsetEnd>342</CharacterOffsetEnd>
            <POS>VB</POS>
            <NER>O</NER>
          </token>
          <token id="3">
            <word>otherwise</word>
            <lemma>otherwise</lemma>
            <CharacterOffsetBegin>343</CharacterOffsetBegin>
            <CharacterOffsetEnd>352</CharacterOffsetEnd>
            <POS>RB</POS>
            <NER>O</NER>
          </token>
          <token id="4">
            <word>he</word>
            <lemma>he</lemma>
            <CharacterOffsetBegin>353</CharacterOffsetBegin>
            <CharacterOffsetEnd>355</CharacterOffsetEnd>
            <POS>PRP</POS>
            <NER>O</NER>
          </token>
          <token id="5">
            <word>has</word>
            <lemma>have</lemma>
            <CharacterOffsetBegin>356</CharacterOffsetBegin>
            <CharacterOffsetEnd>359</CharacterOffsetEnd>
            <POS>VBZ</POS>
            <NER>O</NER>
          </token>
          <token id="6">
            <word>to</word>
            <lemma>to</lemma>
            <CharacterOffsetBegin>360</CharacterOffsetBegin>
            <CharacterOffsetEnd>362</CharacterOffsetEnd>
            <POS>TO</POS>
            <NER>O</NER>
          </token>
          <token id="7">
            <word>sail</word>
            <lemma>sail</lemma>
            <CharacterOffsetBegin>363</CharacterOffsetBegin>
            <CharacterOffsetEnd>367</CharacterOffsetEnd>
            <POS>VB</POS>
            <NER>O</NER>
          </token>
          <token id="8">
            <word>again</word>
            <lemma>again</lemma>
            <CharacterOffsetBegin>368</CharacterOffsetBegin>
            <CharacterOffsetEnd>373</CharacterOffsetEnd>
            <POS>RB</POS>
            <NER>O</NER>
          </token>
          <token id="9">
            <word>.</word>
            <lemma>.</lemma>
            <CharacterOffsetBegin>373</CharacterOffsetBegin>
            <CharacterOffsetEnd>374</CharacterOffsetEnd>
            <POS>.</POS>
            <NER>O</NER>
          </token>
        </tokens>
        <parse>(ROOT (S (S (VP (TO To) (VP (VB prove) (ADVP (RB otherwise))))) (NP (PRP he)) (VP (VBZ has) (S (VP (TO to) (VP (VB sail) (ADVP (RB again)))))) (. .))) </parse>
        <basic-dependencies>
          <dep type="aux">
            <governor idx="2">prove</governor>
            <dependent idx="1">To</dependent>
          </dep>
          <dep type="dep">
            <governor idx="5">has</governor>
            <dependent idx="2">prove</dependent>
          </dep>
          <dep type="advmod">
            <governor idx="2">prove</governor>
            <dependent idx="3">otherwise</dependent>
          </dep>
          <dep type="nsubj">
            <governor idx="5">has</governor>
            <dependent idx="4">he</dependent>
          </dep>
          <dep type="aux">
            <governor idx="7">sail</governor>
            <dependent idx="6">to</dependent>
          </dep>
          <dep type="xcomp">
            <governor idx="5">has</governor>
            <dependent idx="7">sail</dependent>
          </dep>
          <dep type="advmod">
            <governor idx="7">sail</governor>
            <dependent idx="8">again</dependent>
          </dep>
        </basic-dependencies>
        <collapsed-dependencies>
          <dep type="aux">
            <governor idx="2">prove</governor>
            <dependent idx="1">To</dependent>
          </dep>
          <dep type="dep">
            <governor idx="5">has</governor>
            <dependent idx="2">prove</dependent>
          </dep>
          <dep type="advmod">
            <governor idx="2">prove</governor>
            <dependent idx="3">otherwise</dependent>
          </dep>
          <dep type="nsubj">
            <governor idx="5">has</governor>
            <dependent idx="4">he</dependent>
          </dep>
          <dep type="aux">
            <governor idx="7">sail</governor>
            <dependent idx="6">to</dependent>
          </dep>
          <dep type="xcomp">
            <governor idx="5">has</governor>
            <dependent idx="7">sail</dependent>
          </dep>
          <dep type="advmod">
            <governor idx="7">sail</governor>
            <dependent idx="8">again</dependent>
          </dep>
        </collapsed-dependencies>
        <collapsed-ccprocessed-dependencies>
          <dep type="aux">
            <governor idx="2">prove</governor>
            <dependent idx="1">To</dependent>
          </dep>
          <dep type="dep">
            <governor idx="5">has</governor>
            <dependent idx="2">prove</dependent>
          </dep>
          <dep type="advmod">
            <governor idx="2">prove</governor>
            <dependent idx="3">otherwise</dependent>
          </dep>
          <dep type="nsubj">
            <governor idx="5">has</governor>
            <dependent idx="4">he</dependent>
          </dep>
          <dep type="aux">
            <governor idx="7">sail</governor>
            <dependent idx="6">to</dependent>
          </dep>
          <dep type="xcomp">
            <governor idx="5">has</governor>
            <dependent idx="7">sail</dependent>
          </dep>
          <dep type="advmod">
            <governor idx="7">sail</governor>
            <dependent idx="8">again</dependent>
          </dep>
        </collapsed-ccprocessed-dependencies>
      </sentence>
      <sentence id="5">
        <tokens>
          <token id="1">
            <word>http:\/\/www.imdb.com\/title\/tt0044475\/plotsummary\/</word>
            <lemma>http:\/\/www.imdb.com\/title\/tt0044475\/plotsummary\/</lemma>
            <CharacterOffsetBegin>374</CharacterOffsetBegin>
            <CharacterOffsetEnd>422</CharacterOffsetEnd>
            <POS>NN</POS>
            <NER>O</NER>
          </token>
        </tokens>
        <parse>(ROOT (NP (NN http:\/\/www.imdb.com\/title\/tt0044475\/plotsummary\/))) </parse>
        <basic-dependencies/>
        <collapsed-dependencies/>
        <collapsed-ccprocessed-dependencies/>
      </sentence>
    </sentences>
    <coreference>
      <coreference>
        <mention representative="true">
          <sentence>1</sentence>
          <start>9</start>
          <end>10</end>
          <head>9</head>
        </mention>
        <mention>
          <sentence>2</sentence>
          <start>3</start>
          <end>4</end>
          <head>3</head>
        </mention>
        <mention>
          <sentence>2</sentence>
          <start>11</start>
          <end>12</end>
          <head>11</head>
        </mention>
        <mention>
          <sentence>2</sentence>
          <start>14</start>
          <end>15</end>
          <head>14</head>
        </mention>
        <mention>
          <sentence>3</sentence>
          <start>1</start>
          <end>2</end>
          <head>1</head>
        </mention>
        <mention>
          <sentence>3</sentence>
          <start>9</start>
          <end>10</end>
          <head>9</head>
        </mention>
        <mention>
          <sentence>3</sentence>
          <start>22</start>
          <end>23</end>
          <head>22</head>
        </mention>
        <mention>
          <sentence>4</sentence>
          <start>4</start>
          <end>5</end>
          <head>4</head>
        </mention>
      </coreference>
    </coreference>
  </document>
</root>
