<?xml version="1.0" encoding="UTF-8"?>
<?xml-stylesheet href="CoreNLP-to-HTML.xsl" type="text/xsl"?>
<root>
  <document>
    <sentences>
      <sentence id="1">
        <tokens>
          <token id="1">
            <word>Sai</word>
            <lemma>Sai</lemma>
            <CharacterOffsetBegin>0</CharacterOffsetBegin>
            <CharacterOffsetEnd>3</CharacterOffsetEnd>
            <POS>NNP</POS>
            <NER>PERSON</NER>
          </token>
          <token id="2">
            <word>,</word>
            <lemma>,</lemma>
            <CharacterOffsetBegin>3</CharacterOffsetBegin>
            <CharacterOffsetEnd>4</CharacterOffsetEnd>
            <POS>,</POS>
            <NER>O</NER>
          </token>
          <token id="3">
            <word>a</word>
            <lemma>a</lemma>
            <CharacterOffsetBegin>5</CharacterOffsetBegin>
            <CharacterOffsetEnd>6</CharacterOffsetEnd>
            <POS>DT</POS>
            <NER>O</NER>
          </token>
          <token id="4">
            <word>young</word>
            <lemma>young</lemma>
            <CharacterOffsetBegin>7</CharacterOffsetBegin>
            <CharacterOffsetEnd>12</CharacterOffsetEnd>
            <POS>JJ</POS>
            <NER>O</NER>
          </token>
          <token id="5">
            <word>artist</word>
            <lemma>artist</lemma>
            <CharacterOffsetBegin>13</CharacterOffsetBegin>
            <CharacterOffsetEnd>19</CharacterOffsetEnd>
            <POS>NN</POS>
            <NER>O</NER>
          </token>
          <token id="6">
            <word>living</word>
            <lemma>living</lemma>
            <CharacterOffsetBegin>20</CharacterOffsetBegin>
            <CharacterOffsetEnd>26</CharacterOffsetEnd>
            <POS>NN</POS>
            <NER>O</NER>
          </token>
          <token id="7">
            <word>in</word>
            <lemma>in</lemma>
            <CharacterOffsetBegin>27</CharacterOffsetBegin>
            <CharacterOffsetEnd>29</CharacterOffsetEnd>
            <POS>IN</POS>
            <NER>O</NER>
          </token>
          <token id="8">
            <word>a</word>
            <lemma>a</lemma>
            <CharacterOffsetBegin>30</CharacterOffsetBegin>
            <CharacterOffsetEnd>31</CharacterOffsetEnd>
            <POS>DT</POS>
            <NER>O</NER>
          </token>
          <token id="9">
            <word>downtown</word>
            <lemma>downtown</lemma>
            <CharacterOffsetBegin>32</CharacterOffsetBegin>
            <CharacterOffsetEnd>40</CharacterOffsetEnd>
            <POS>NN</POS>
            <NER>O</NER>
          </token>
          <token id="10">
            <word>warehouse</word>
            <lemma>warehouse</lemma>
            <CharacterOffsetBegin>41</CharacterOffsetBegin>
            <CharacterOffsetEnd>50</CharacterOffsetEnd>
            <POS>NN</POS>
            <NER>O</NER>
          </token>
          <token id="11">
            <word>delves</word>
            <lemma>delve</lemma>
            <CharacterOffsetBegin>51</CharacterOffsetBegin>
            <CharacterOffsetEnd>57</CharacterOffsetEnd>
            <POS>VBZ</POS>
            <NER>O</NER>
          </token>
          <token id="12">
            <word>into</word>
            <lemma>into</lemma>
            <CharacterOffsetBegin>58</CharacterOffsetBegin>
            <CharacterOffsetEnd>62</CharacterOffsetEnd>
            <POS>IN</POS>
            <NER>O</NER>
          </token>
          <token id="13">
            <word>an</word>
            <lemma>a</lemma>
            <CharacterOffsetBegin>63</CharacterOffsetBegin>
            <CharacterOffsetEnd>65</CharacterOffsetEnd>
            <POS>DT</POS>
            <NER>O</NER>
          </token>
          <token id="14">
            <word>ancient</word>
            <lemma>ancient</lemma>
            <CharacterOffsetBegin>66</CharacterOffsetBegin>
            <CharacterOffsetEnd>73</CharacterOffsetEnd>
            <POS>JJ</POS>
            <NER>O</NER>
          </token>
          <token id="15">
            <word>world</word>
            <lemma>world</lemma>
            <CharacterOffsetBegin>74</CharacterOffsetBegin>
            <CharacterOffsetEnd>79</CharacterOffsetEnd>
            <POS>NN</POS>
            <NER>O</NER>
          </token>
          <token id="16">
            <word>of</word>
            <lemma>of</lemma>
            <CharacterOffsetBegin>80</CharacterOffsetBegin>
            <CharacterOffsetEnd>82</CharacterOffsetEnd>
            <POS>IN</POS>
            <NER>O</NER>
          </token>
          <token id="17">
            <word>blood</word>
            <lemma>blood</lemma>
            <CharacterOffsetBegin>83</CharacterOffsetBegin>
            <CharacterOffsetEnd>88</CharacterOffsetEnd>
            <POS>NN</POS>
            <NER>O</NER>
          </token>
          <token id="18">
            <word>and</word>
            <lemma>and</lemma>
            <CharacterOffsetBegin>89</CharacterOffsetBegin>
            <CharacterOffsetEnd>92</CharacterOffsetEnd>
            <POS>CC</POS>
            <NER>O</NER>
          </token>
          <token id="19">
            <word>lust</word>
            <lemma>lust</lemma>
            <CharacterOffsetBegin>93</CharacterOffsetBegin>
            <CharacterOffsetEnd>97</CharacterOffsetEnd>
            <POS>NN</POS>
            <NER>O</NER>
          </token>
          <token id="20">
            <word>.</word>
            <lemma>.</lemma>
            <CharacterOffsetBegin>97</CharacterOffsetBegin>
            <CharacterOffsetEnd>98</CharacterOffsetEnd>
            <POS>.</POS>
            <NER>O</NER>
          </token>
        </tokens>
        <parse>(ROOT (S (NP (NP (NNP Sai)) (, ,) (NP (NP (DT a) (JJ young) (NN artist) (NN living)) (PP (IN in) (NP (DT a) (NN downtown) (NN warehouse))))) (VP (VBZ delves) (PP (IN into) (NP (NP (DT an) (JJ ancient) (NN world)) (PP (IN of) (NP (NN blood) (CC and) (NN lust)))))) (. .))) </parse>
        <basic-dependencies>
          <dep type="nsubj">
            <governor idx="11">delves</governor>
            <dependent idx="1">Sai</dependent>
          </dep>
          <dep type="det">
            <governor idx="6">living</governor>
            <dependent idx="3">a</dependent>
          </dep>
          <dep type="amod">
            <governor idx="6">living</governor>
            <dependent idx="4">young</dependent>
          </dep>
          <dep type="nn">
            <governor idx="6">living</governor>
            <dependent idx="5">artist</dependent>
          </dep>
          <dep type="appos">
            <governor idx="1">Sai</governor>
            <dependent idx="6">living</dependent>
          </dep>
          <dep type="prep">
            <governor idx="6">living</governor>
            <dependent idx="7">in</dependent>
          </dep>
          <dep type="det">
            <governor idx="10">warehouse</governor>
            <dependent idx="8">a</dependent>
          </dep>
          <dep type="nn">
            <governor idx="10">warehouse</governor>
            <dependent idx="9">downtown</dependent>
          </dep>
          <dep type="pobj">
            <governor idx="7">in</governor>
            <dependent idx="10">warehouse</dependent>
          </dep>
          <dep type="prep">
            <governor idx="11">delves</governor>
            <dependent idx="12">into</dependent>
          </dep>
          <dep type="det">
            <governor idx="15">world</governor>
            <dependent idx="13">an</dependent>
          </dep>
          <dep type="amod">
            <governor idx="15">world</governor>
            <dependent idx="14">ancient</dependent>
          </dep>
          <dep type="pobj">
            <governor idx="12">into</governor>
            <dependent idx="15">world</dependent>
          </dep>
          <dep type="prep">
            <governor idx="15">world</governor>
            <dependent idx="16">of</dependent>
          </dep>
          <dep type="pobj">
            <governor idx="16">of</governor>
            <dependent idx="17">blood</dependent>
          </dep>
          <dep type="cc">
            <governor idx="17">blood</governor>
            <dependent idx="18">and</dependent>
          </dep>
          <dep type="conj">
            <governor idx="17">blood</governor>
            <dependent idx="19">lust</dependent>
          </dep>
        </basic-dependencies>
        <collapsed-dependencies>
          <dep type="nsubj">
            <governor idx="11">delves</governor>
            <dependent idx="1">Sai</dependent>
          </dep>
          <dep type="det">
            <governor idx="6">living</governor>
            <dependent idx="3">a</dependent>
          </dep>
          <dep type="amod">
            <governor idx="6">living</governor>
            <dependent idx="4">young</dependent>
          </dep>
          <dep type="nn">
            <governor idx="6">living</governor>
            <dependent idx="5">artist</dependent>
          </dep>
          <dep type="appos">
            <governor idx="1">Sai</governor>
            <dependent idx="6">living</dependent>
          </dep>
          <dep type="det">
            <governor idx="10">warehouse</governor>
            <dependent idx="8">a</dependent>
          </dep>
          <dep type="nn">
            <governor idx="10">warehouse</governor>
            <dependent idx="9">downtown</dependent>
          </dep>
          <dep type="prep_in">
            <governor idx="6">living</governor>
            <dependent idx="10">warehouse</dependent>
          </dep>
          <dep type="det">
            <governor idx="15">world</governor>
            <dependent idx="13">an</dependent>
          </dep>
          <dep type="amod">
            <governor idx="15">world</governor>
            <dependent idx="14">ancient</dependent>
          </dep>
          <dep type="prep_into">
            <governor idx="11">delves</governor>
            <dependent idx="15">world</dependent>
          </dep>
          <dep type="prep_of">
            <governor idx="15">world</governor>
            <dependent idx="17">blood</dependent>
          </dep>
          <dep type="conj_and">
            <governor idx="17">blood</governor>
            <dependent idx="19">lust</dependent>
          </dep>
        </collapsed-dependencies>
        <collapsed-ccprocessed-dependencies>
          <dep type="nsubj">
            <governor idx="11">delves</governor>
            <dependent idx="1">Sai</dependent>
          </dep>
          <dep type="det">
            <governor idx="6">living</governor>
            <dependent idx="3">a</dependent>
          </dep>
          <dep type="amod">
            <governor idx="6">living</governor>
            <dependent idx="4">young</dependent>
          </dep>
          <dep type="nn">
            <governor idx="6">living</governor>
            <dependent idx="5">artist</dependent>
          </dep>
          <dep type="appos">
            <governor idx="1">Sai</governor>
            <dependent idx="6">living</dependent>
          </dep>
          <dep type="det">
            <governor idx="10">warehouse</governor>
            <dependent idx="8">a</dependent>
          </dep>
          <dep type="nn">
            <governor idx="10">warehouse</governor>
            <dependent idx="9">downtown</dependent>
          </dep>
          <dep type="prep_in">
            <governor idx="6">living</governor>
            <dependent idx="10">warehouse</dependent>
          </dep>
          <dep type="det">
            <governor idx="15">world</governor>
            <dependent idx="13">an</dependent>
          </dep>
          <dep type="amod">
            <governor idx="15">world</governor>
            <dependent idx="14">ancient</dependent>
          </dep>
          <dep type="prep_into">
            <governor idx="11">delves</governor>
            <dependent idx="15">world</dependent>
          </dep>
          <dep type="prep_of">
            <governor idx="15">world</governor>
            <dependent idx="17">blood</dependent>
          </dep>
          <dep type="prep_of">
            <governor idx="15">world</governor>
            <dependent idx="19">lust</dependent>
          </dep>
          <dep type="conj_and">
            <governor idx="17">blood</governor>
            <dependent idx="19">lust</dependent>
          </dep>
        </collapsed-ccprocessed-dependencies>
      </sentence>
      <sentence id="2">
        <tokens>
          <token id="1">
            <word>An</word>
            <lemma>a</lemma>
            <CharacterOffsetBegin>99</CharacterOffsetBegin>
            <CharacterOffsetEnd>101</CharacterOffsetEnd>
            <POS>DT</POS>
            <NER>O</NER>
          </token>
          <token id="2">
            <word>enigmatic</word>
            <lemma>enigmatic</lemma>
            <CharacterOffsetBegin>102</CharacterOffsetBegin>
            <CharacterOffsetEnd>111</CharacterOffsetEnd>
            <POS>JJ</POS>
            <NER>O</NER>
          </token>
          <token id="3">
            <word>foreigner</word>
            <lemma>foreigner</lemma>
            <CharacterOffsetBegin>112</CharacterOffsetBegin>
            <CharacterOffsetEnd>121</CharacterOffsetEnd>
            <POS>NN</POS>
            <NER>O</NER>
          </token>
          <token id="4">
            <word>seduces</word>
            <lemma>seduce</lemma>
            <CharacterOffsetBegin>122</CharacterOffsetBegin>
            <CharacterOffsetEnd>129</CharacterOffsetEnd>
            <POS>VBZ</POS>
            <NER>O</NER>
          </token>
          <token id="5">
            <word>her</word>
            <lemma>she</lemma>
            <CharacterOffsetBegin>130</CharacterOffsetBegin>
            <CharacterOffsetEnd>133</CharacterOffsetEnd>
            <POS>PRP$</POS>
            <NER>O</NER>
          </token>
          <token id="6">
            <word>to</word>
            <lemma>to</lemma>
            <CharacterOffsetBegin>134</CharacterOffsetBegin>
            <CharacterOffsetEnd>136</CharacterOffsetEnd>
            <POS>TO</POS>
            <NER>O</NER>
          </token>
          <token id="7">
            <word>try</word>
            <lemma>try</lemma>
            <CharacterOffsetBegin>137</CharacterOffsetBegin>
            <CharacterOffsetEnd>140</CharacterOffsetEnd>
            <POS>VB</POS>
            <NER>O</NER>
          </token>
          <token id="8">
            <word>a</word>
            <lemma>a</lemma>
            <CharacterOffsetBegin>141</CharacterOffsetBegin>
            <CharacterOffsetEnd>142</CharacterOffsetEnd>
            <POS>DT</POS>
            <NER>O</NER>
          </token>
          <token id="9">
            <word>long</word>
            <lemma>long</lemma>
            <CharacterOffsetBegin>143</CharacterOffsetBegin>
            <CharacterOffsetEnd>147</CharacterOffsetEnd>
            <POS>JJ</POS>
            <NER>O</NER>
          </token>
          <token id="10">
            <word>forgotten</word>
            <lemma>forget</lemma>
            <CharacterOffsetBegin>148</CharacterOffsetBegin>
            <CharacterOffsetEnd>157</CharacterOffsetEnd>
            <POS>VBN</POS>
            <NER>O</NER>
          </token>
          <token id="11">
            <word>drug</word>
            <lemma>drug</lemma>
            <CharacterOffsetBegin>158</CharacterOffsetBegin>
            <CharacterOffsetEnd>162</CharacterOffsetEnd>
            <POS>NN</POS>
            <NER>O</NER>
          </token>
          <token id="12">
            <word>making</word>
            <lemma>make</lemma>
            <CharacterOffsetBegin>163</CharacterOffsetBegin>
            <CharacterOffsetEnd>169</CharacterOffsetEnd>
            <POS>VBG</POS>
            <NER>O</NER>
          </token>
          <token id="13">
            <word>her</word>
            <lemma>she</lemma>
            <CharacterOffsetBegin>170</CharacterOffsetBegin>
            <CharacterOffsetEnd>173</CharacterOffsetEnd>
            <POS>PRP$</POS>
            <NER>O</NER>
          </token>
          <token id="14">
            <word>the</word>
            <lemma>the</lemma>
            <CharacterOffsetBegin>174</CharacterOffsetBegin>
            <CharacterOffsetEnd>177</CharacterOffsetEnd>
            <POS>DT</POS>
            <NER>O</NER>
          </token>
          <token id="15">
            <word>prey</word>
            <lemma>prey</lemma>
            <CharacterOffsetBegin>178</CharacterOffsetBegin>
            <CharacterOffsetEnd>182</CharacterOffsetEnd>
            <POS>NN</POS>
            <NER>O</NER>
          </token>
          <token id="16">
            <word>of</word>
            <lemma>of</lemma>
            <CharacterOffsetBegin>183</CharacterOffsetBegin>
            <CharacterOffsetEnd>185</CharacterOffsetEnd>
            <POS>IN</POS>
            <NER>O</NER>
          </token>
          <token id="17">
            <word>a</word>
            <lemma>a</lemma>
            <CharacterOffsetBegin>186</CharacterOffsetBegin>
            <CharacterOffsetEnd>187</CharacterOffsetEnd>
            <POS>DT</POS>
            <NER>O</NER>
          </token>
          <token id="18">
            <word>dimensional</word>
            <lemma>dimensional</lemma>
            <CharacterOffsetBegin>188</CharacterOffsetBegin>
            <CharacterOffsetEnd>199</CharacterOffsetEnd>
            <POS>JJ</POS>
            <NER>O</NER>
          </token>
          <token id="19">
            <word>vampire</word>
            <lemma>vampire</lemma>
            <CharacterOffsetBegin>200</CharacterOffsetBegin>
            <CharacterOffsetEnd>207</CharacterOffsetEnd>
            <POS>NN</POS>
            <NER>O</NER>
          </token>
          <token id="20">
            <word>who</word>
            <lemma>who</lemma>
            <CharacterOffsetBegin>208</CharacterOffsetBegin>
            <CharacterOffsetEnd>211</CharacterOffsetEnd>
            <POS>WP</POS>
            <NER>O</NER>
          </token>
          <token id="21">
            <word>needs</word>
            <lemma>need</lemma>
            <CharacterOffsetBegin>212</CharacterOffsetBegin>
            <CharacterOffsetEnd>217</CharacterOffsetEnd>
            <POS>VBZ</POS>
            <NER>O</NER>
          </token>
          <token id="22">
            <word>her</word>
            <lemma>she</lemma>
            <CharacterOffsetBegin>218</CharacterOffsetBegin>
            <CharacterOffsetEnd>221</CharacterOffsetEnd>
            <POS>PRP$</POS>
            <NER>O</NER>
          </token>
          <token id="23">
            <word>new</word>
            <lemma>new</lemma>
            <CharacterOffsetBegin>222</CharacterOffsetBegin>
            <CharacterOffsetEnd>225</CharacterOffsetEnd>
            <POS>JJ</POS>
            <NER>O</NER>
          </token>
          <token id="24">
            <word>found</word>
            <lemma>find</lemma>
            <CharacterOffsetBegin>226</CharacterOffsetBegin>
            <CharacterOffsetEnd>231</CharacterOffsetEnd>
            <POS>VBN</POS>
            <NER>O</NER>
          </token>
          <token id="25">
            <word>hunger</word>
            <lemma>hunger</lemma>
            <CharacterOffsetBegin>232</CharacterOffsetBegin>
            <CharacterOffsetEnd>238</CharacterOffsetEnd>
            <POS>NN</POS>
            <NER>O</NER>
          </token>
          <token id="26">
            <word>for</word>
            <lemma>for</lemma>
            <CharacterOffsetBegin>239</CharacterOffsetBegin>
            <CharacterOffsetEnd>242</CharacterOffsetEnd>
            <POS>IN</POS>
            <NER>O</NER>
          </token>
          <token id="27">
            <word>blood</word>
            <lemma>blood</lemma>
            <CharacterOffsetBegin>243</CharacterOffsetBegin>
            <CharacterOffsetEnd>248</CharacterOffsetEnd>
            <POS>NN</POS>
            <NER>O</NER>
          </token>
          <token id="28">
            <word>to</word>
            <lemma>to</lemma>
            <CharacterOffsetBegin>249</CharacterOffsetBegin>
            <CharacterOffsetEnd>251</CharacterOffsetEnd>
            <POS>TO</POS>
            <NER>O</NER>
          </token>
          <token id="29">
            <word>cross</word>
            <lemma>cross</lemma>
            <CharacterOffsetBegin>252</CharacterOffsetBegin>
            <CharacterOffsetEnd>257</CharacterOffsetEnd>
            <POS>VB</POS>
            <NER>O</NER>
          </token>
          <token id="30">
            <word>over</word>
            <lemma>over</lemma>
            <CharacterOffsetBegin>258</CharacterOffsetBegin>
            <CharacterOffsetEnd>262</CharacterOffsetEnd>
            <POS>RP</POS>
            <NER>O</NER>
          </token>
          <token id="31">
            <word>from</word>
            <lemma>from</lemma>
            <CharacterOffsetBegin>263</CharacterOffsetBegin>
            <CharacterOffsetEnd>267</CharacterOffsetEnd>
            <POS>IN</POS>
            <NER>O</NER>
          </token>
          <token id="32">
            <word>his</word>
            <lemma>he</lemma>
            <CharacterOffsetBegin>268</CharacterOffsetBegin>
            <CharacterOffsetEnd>271</CharacterOffsetEnd>
            <POS>PRP$</POS>
            <NER>O</NER>
          </token>
          <token id="33">
            <word>world</word>
            <lemma>world</lemma>
            <CharacterOffsetBegin>272</CharacterOffsetBegin>
            <CharacterOffsetEnd>277</CharacterOffsetEnd>
            <POS>NN</POS>
            <NER>O</NER>
          </token>
          <token id="34">
            <word>to</word>
            <lemma>to</lemma>
            <CharacterOffsetBegin>278</CharacterOffsetBegin>
            <CharacterOffsetEnd>280</CharacterOffsetEnd>
            <POS>TO</POS>
            <NER>O</NER>
          </token>
          <token id="35">
            <word>hers</word>
            <lemma>hers</lemma>
            <CharacterOffsetBegin>281</CharacterOffsetBegin>
            <CharacterOffsetEnd>285</CharacterOffsetEnd>
            <POS>NNS</POS>
            <NER>O</NER>
          </token>
          <token id="36">
            <word>.</word>
            <lemma>.</lemma>
            <CharacterOffsetBegin>285</CharacterOffsetBegin>
            <CharacterOffsetEnd>286</CharacterOffsetEnd>
            <POS>.</POS>
            <NER>O</NER>
          </token>
        </tokens>
        <parse>(ROOT (S (NP (DT An) (JJ enigmatic) (NN foreigner)) (VP (VBZ seduces) (S (NP (PRP$ her)) (VP (TO to) (VP (VB try) (NP (NP (DT a) (JJ long)) (VP (VBN forgotten) (NP (NN drug)) (S (VP (VBG making) (NP (NP (PRP$ her) (NP (NP (DT the) (NN prey)) (PP (IN of) (NP (DT a) (JJ dimensional) (NN vampire))))) (SBAR (WHNP (WP who)) (S (VP (VBZ needs) (NP (NP (PRP$ her) (JJ new)) (VP (VBN found) (NP (NN hunger)) (PP (IN for) (NP (NN blood))) (S (VP (TO to) (VP (VB cross) (PRT (RP over)) (PP (IN from) (NP (PRP$ his) (NN world))) (PP (TO to) (NP (NNS hers)))))))))))))))))))) (. .))) </parse>
        <basic-dependencies>
          <dep type="det">
            <governor idx="3">foreigner</governor>
            <dependent idx="1">An</dependent>
          </dep>
          <dep type="amod">
            <governor idx="3">foreigner</governor>
            <dependent idx="2">enigmatic</dependent>
          </dep>
          <dep type="nsubj">
            <governor idx="4">seduces</governor>
            <dependent idx="3">foreigner</dependent>
          </dep>
          <dep type="nsubj">
            <governor idx="7">try</governor>
            <dependent idx="5">her</dependent>
          </dep>
          <dep type="aux">
            <governor idx="7">try</governor>
            <dependent idx="6">to</dependent>
          </dep>
          <dep type="xcomp">
            <governor idx="4">seduces</governor>
            <dependent idx="7">try</dependent>
          </dep>
          <dep type="det">
            <governor idx="9">long</governor>
            <dependent idx="8">a</dependent>
          </dep>
          <dep type="dobj">
            <governor idx="7">try</governor>
            <dependent idx="9">long</dependent>
          </dep>
          <dep type="partmod">
            <governor idx="9">long</governor>
            <dependent idx="10">forgotten</dependent>
          </dep>
          <dep type="dobj">
            <governor idx="10">forgotten</governor>
            <dependent idx="11">drug</dependent>
          </dep>
          <dep type="xcomp">
            <governor idx="10">forgotten</governor>
            <dependent idx="12">making</dependent>
          </dep>
          <dep type="poss">
            <governor idx="15">prey</governor>
            <dependent idx="13">her</dependent>
          </dep>
          <dep type="det">
            <governor idx="15">prey</governor>
            <dependent idx="14">the</dependent>
          </dep>
          <dep type="dobj">
            <governor idx="12">making</governor>
            <dependent idx="15">prey</dependent>
          </dep>
          <dep type="prep">
            <governor idx="15">prey</governor>
            <dependent idx="16">of</dependent>
          </dep>
          <dep type="det">
            <governor idx="19">vampire</governor>
            <dependent idx="17">a</dependent>
          </dep>
          <dep type="amod">
            <governor idx="19">vampire</governor>
            <dependent idx="18">dimensional</dependent>
          </dep>
          <dep type="pobj">
            <governor idx="16">of</governor>
            <dependent idx="19">vampire</dependent>
          </dep>
          <dep type="nsubj">
            <governor idx="21">needs</governor>
            <dependent idx="20">who</dependent>
          </dep>
          <dep type="rcmod">
            <governor idx="15">prey</governor>
            <dependent idx="21">needs</dependent>
          </dep>
          <dep type="poss">
            <governor idx="23">new</governor>
            <dependent idx="22">her</dependent>
          </dep>
          <dep type="dobj">
            <governor idx="21">needs</governor>
            <dependent idx="23">new</dependent>
          </dep>
          <dep type="partmod">
            <governor idx="23">new</governor>
            <dependent idx="24">found</dependent>
          </dep>
          <dep type="dobj">
            <governor idx="24">found</governor>
            <dependent idx="25">hunger</dependent>
          </dep>
          <dep type="prep">
            <governor idx="24">found</governor>
            <dependent idx="26">for</dependent>
          </dep>
          <dep type="pobj">
            <governor idx="26">for</governor>
            <dependent idx="27">blood</dependent>
          </dep>
          <dep type="aux">
            <governor idx="29">cross</governor>
            <dependent idx="28">to</dependent>
          </dep>
          <dep type="xcomp">
            <governor idx="24">found</governor>
            <dependent idx="29">cross</dependent>
          </dep>
          <dep type="prt">
            <governor idx="29">cross</governor>
            <dependent idx="30">over</dependent>
          </dep>
          <dep type="prep">
            <governor idx="29">cross</governor>
            <dependent idx="31">from</dependent>
          </dep>
          <dep type="poss">
            <governor idx="33">world</governor>
            <dependent idx="32">his</dependent>
          </dep>
          <dep type="pobj">
            <governor idx="31">from</governor>
            <dependent idx="33">world</dependent>
          </dep>
          <dep type="prep">
            <governor idx="29">cross</governor>
            <dependent idx="34">to</dependent>
          </dep>
          <dep type="pobj">
            <governor idx="34">to</governor>
            <dependent idx="35">hers</dependent>
          </dep>
        </basic-dependencies>
        <collapsed-dependencies>
          <dep type="det">
            <governor idx="3">foreigner</governor>
            <dependent idx="1">An</dependent>
          </dep>
          <dep type="amod">
            <governor idx="3">foreigner</governor>
            <dependent idx="2">enigmatic</dependent>
          </dep>
          <dep type="nsubj">
            <governor idx="4">seduces</governor>
            <dependent idx="3">foreigner</dependent>
          </dep>
          <dep type="nsubj">
            <governor idx="7">try</governor>
            <dependent idx="5">her</dependent>
          </dep>
          <dep type="aux">
            <governor idx="7">try</governor>
            <dependent idx="6">to</dependent>
          </dep>
          <dep type="xcomp">
            <governor idx="4">seduces</governor>
            <dependent idx="7">try</dependent>
          </dep>
          <dep type="det">
            <governor idx="9">long</governor>
            <dependent idx="8">a</dependent>
          </dep>
          <dep type="dobj">
            <governor idx="7">try</governor>
            <dependent idx="9">long</dependent>
          </dep>
          <dep type="partmod">
            <governor idx="9">long</governor>
            <dependent idx="10">forgotten</dependent>
          </dep>
          <dep type="dobj">
            <governor idx="10">forgotten</governor>
            <dependent idx="11">drug</dependent>
          </dep>
          <dep type="xcomp">
            <governor idx="10">forgotten</governor>
            <dependent idx="12">making</dependent>
          </dep>
          <dep type="poss">
            <governor idx="15">prey</governor>
            <dependent idx="13">her</dependent>
          </dep>
          <dep type="det">
            <governor idx="15">prey</governor>
            <dependent idx="14">the</dependent>
          </dep>
          <dep type="dobj">
            <governor idx="12">making</governor>
            <dependent idx="15">prey</dependent>
          </dep>
          <dep type="det">
            <governor idx="19">vampire</governor>
            <dependent idx="17">a</dependent>
          </dep>
          <dep type="amod">
            <governor idx="19">vampire</governor>
            <dependent idx="18">dimensional</dependent>
          </dep>
          <dep type="prep_of">
            <governor idx="15">prey</governor>
            <dependent idx="19">vampire</dependent>
          </dep>
          <dep type="nsubj">
            <governor idx="21">needs</governor>
            <dependent idx="20">who</dependent>
          </dep>
          <dep type="rcmod">
            <governor idx="15">prey</governor>
            <dependent idx="21">needs</dependent>
          </dep>
          <dep type="poss">
            <governor idx="23">new</governor>
            <dependent idx="22">her</dependent>
          </dep>
          <dep type="dobj">
            <governor idx="21">needs</governor>
            <dependent idx="23">new</dependent>
          </dep>
          <dep type="partmod">
            <governor idx="23">new</governor>
            <dependent idx="24">found</dependent>
          </dep>
          <dep type="dobj">
            <governor idx="24">found</governor>
            <dependent idx="25">hunger</dependent>
          </dep>
          <dep type="prep_for">
            <governor idx="24">found</governor>
            <dependent idx="27">blood</dependent>
          </dep>
          <dep type="aux">
            <governor idx="29">cross</governor>
            <dependent idx="28">to</dependent>
          </dep>
          <dep type="xcomp">
            <governor idx="24">found</governor>
            <dependent idx="29">cross</dependent>
          </dep>
          <dep type="prt">
            <governor idx="29">cross</governor>
            <dependent idx="30">over</dependent>
          </dep>
          <dep type="poss">
            <governor idx="33">world</governor>
            <dependent idx="32">his</dependent>
          </dep>
          <dep type="prep_from">
            <governor idx="29">cross</governor>
            <dependent idx="33">world</dependent>
          </dep>
          <dep type="prep_to">
            <governor idx="29">cross</governor>
            <dependent idx="35">hers</dependent>
          </dep>
        </collapsed-dependencies>
        <collapsed-ccprocessed-dependencies>
          <dep type="det">
            <governor idx="3">foreigner</governor>
            <dependent idx="1">An</dependent>
          </dep>
          <dep type="amod">
            <governor idx="3">foreigner</governor>
            <dependent idx="2">enigmatic</dependent>
          </dep>
          <dep type="nsubj">
            <governor idx="4">seduces</governor>
            <dependent idx="3">foreigner</dependent>
          </dep>
          <dep type="nsubj">
            <governor idx="7">try</governor>
            <dependent idx="5">her</dependent>
          </dep>
          <dep type="aux">
            <governor idx="7">try</governor>
            <dependent idx="6">to</dependent>
          </dep>
          <dep type="xcomp">
            <governor idx="4">seduces</governor>
            <dependent idx="7">try</dependent>
          </dep>
          <dep type="det">
            <governor idx="9">long</governor>
            <dependent idx="8">a</dependent>
          </dep>
          <dep type="dobj">
            <governor idx="7">try</governor>
            <dependent idx="9">long</dependent>
          </dep>
          <dep type="partmod">
            <governor idx="9">long</governor>
            <dependent idx="10">forgotten</dependent>
          </dep>
          <dep type="dobj">
            <governor idx="10">forgotten</governor>
            <dependent idx="11">drug</dependent>
          </dep>
          <dep type="xcomp">
            <governor idx="10">forgotten</governor>
            <dependent idx="12">making</dependent>
          </dep>
          <dep type="poss">
            <governor idx="15">prey</governor>
            <dependent idx="13">her</dependent>
          </dep>
          <dep type="det">
            <governor idx="15">prey</governor>
            <dependent idx="14">the</dependent>
          </dep>
          <dep type="dobj">
            <governor idx="12">making</governor>
            <dependent idx="15">prey</dependent>
          </dep>
          <dep type="det">
            <governor idx="19">vampire</governor>
            <dependent idx="17">a</dependent>
          </dep>
          <dep type="amod">
            <governor idx="19">vampire</governor>
            <dependent idx="18">dimensional</dependent>
          </dep>
          <dep type="prep_of">
            <governor idx="15">prey</governor>
            <dependent idx="19">vampire</dependent>
          </dep>
          <dep type="nsubj">
            <governor idx="21">needs</governor>
            <dependent idx="20">who</dependent>
          </dep>
          <dep type="rcmod">
            <governor idx="15">prey</governor>
            <dependent idx="21">needs</dependent>
          </dep>
          <dep type="poss">
            <governor idx="23">new</governor>
            <dependent idx="22">her</dependent>
          </dep>
          <dep type="dobj">
            <governor idx="21">needs</governor>
            <dependent idx="23">new</dependent>
          </dep>
          <dep type="partmod">
            <governor idx="23">new</governor>
            <dependent idx="24">found</dependent>
          </dep>
          <dep type="dobj">
            <governor idx="24">found</governor>
            <dependent idx="25">hunger</dependent>
          </dep>
          <dep type="prep_for">
            <governor idx="24">found</governor>
            <dependent idx="27">blood</dependent>
          </dep>
          <dep type="aux">
            <governor idx="29">cross</governor>
            <dependent idx="28">to</dependent>
          </dep>
          <dep type="xcomp">
            <governor idx="24">found</governor>
            <dependent idx="29">cross</dependent>
          </dep>
          <dep type="prt">
            <governor idx="29">cross</governor>
            <dependent idx="30">over</dependent>
          </dep>
          <dep type="poss">
            <governor idx="33">world</governor>
            <dependent idx="32">his</dependent>
          </dep>
          <dep type="prep_from">
            <governor idx="29">cross</governor>
            <dependent idx="33">world</dependent>
          </dep>
          <dep type="prep_to">
            <governor idx="29">cross</governor>
            <dependent idx="35">hers</dependent>
          </dep>
        </collapsed-ccprocessed-dependencies>
      </sentence>
    </sentences>
    <coreference>
      <coreference>
        <mention representative="true">
          <sentence>1</sentence>
          <start>1</start>
          <end>11</end>
          <head>1</head>
        </mention>
        <mention>
          <sentence>1</sentence>
          <start>1</start>
          <end>2</end>
          <head>1</head>
        </mention>
      </coreference>
      <coreference>
        <mention representative="true">
          <sentence>2</sentence>
          <start>17</start>
          <end>20</end>
          <head>19</head>
        </mention>
        <mention>
          <sentence>2</sentence>
          <start>32</start>
          <end>33</end>
          <head>32</head>
        </mention>
      </coreference>
      <coreference>
        <mention representative="true">
          <sentence>1</sentence>
          <start>13</start>
          <end>20</end>
          <head>15</head>
        </mention>
        <mention>
          <sentence>2</sentence>
          <start>32</start>
          <end>34</end>
          <head>33</head>
        </mention>
      </coreference>
      <coreference>
        <mention representative="true">
          <sentence>2</sentence>
          <start>5</start>
          <end>6</end>
          <head>5</head>
        </mention>
        <mention>
          <sentence>2</sentence>
          <start>13</start>
          <end>14</end>
          <head>13</head>
        </mention>
        <mention>
          <sentence>2</sentence>
          <start>22</start>
          <end>23</end>
          <head>22</head>
        </mention>
        <mention>
          <sentence>2</sentence>
          <start>35</start>
          <end>36</end>
          <head>35</head>
        </mention>
      </coreference>
    </coreference>
  </document>
</root>
