[{"1": {"28": {"token_id": "28", "token": {"word": "her", "lemma": "she", "POS": "PRP$", "NER": "O"}}}, "2": {"20": {"token_id": "20", "token": {"word": "her", "lemma": "she", "POS": "PRP$", "NER": "O"}}}, "3": {"19": {"token_id": "19", "token": {"word": "she", "lemma": "she", "POS": "PRP", "NER": "O"}}}}, {"5": {"8": {"token_id": "8", "token": {"word": "her", "lemma": "she", "POS": "PRP$", "NER": "O"}}}, "6": {"5": {"token_id": "5", "token": {"word": "her", "lemma": "she", "POS": "PRP$", "NER": "O"}}}, "7": {"20": {"token_id": "20", "token": {"word": "her", "lemma": "she", "POS": "PRP", "NER": "O"}}}}, {"1": {"16": {"token_id": "16", "token": {"word": "mother", "lemma": "mother", "POS": "NN", "NER": "O"}}}}, {"2": {"9": {"token_id": "9", "token": {"word": "women", "lemma": "woman", "POS": "NNS", "NER": "O"}}}, "3": {"26": {"token_id": "26", "token": {"word": "grandmother", "lemma": "grandmother", "POS": "NN", "NER": "O"}}}, "5": {"9": {"token_id": "9", "token": {"word": "aunt", "lemma": "aunt", "POS": "NN", "NER": "O"}}}, "6": {"15": {"token_id": "15", "token": {"word": "her", "lemma": "she", "POS": "PRP$", "NER": "O"}}}, "7": {"10": {"token_id": "10", "token": {"word": "her", "lemma": "she", "POS": "PRP$", "NER": "O"}}}, "12": {"22": {"token_id": "22", "token": {"word": "women", "lemma": "woman", "POS": "NNS", "NER": "O"}}}, "14": {"4": {"token_id": "4", "token": {"word": "women", "lemma": "woman", "POS": "NNS", "NER": "O"}}}, "15": {"40": {"token_id": "40", "token": {"word": "her", "lemma": "she", "POS": "PRP", "NER": "O"}}}, "16": {"35": {"token_id": "35", "token": {"word": "her", "lemma": "she", "POS": "PRP$", "NER": "O"}}}, "17": {"31": {"token_id": "31", "token": {"word": "her", "lemma": "she", "POS": "PRP$", "NER": "O"}}}, "18": {"2": {"token_id": "2", "token": {"word": "women", "lemma": "woman", "POS": "NNS", "NER": "O"}}}, "19": {"2": {"token_id": "2", "token": {"word": "women", "lemma": "woman", "POS": "NNS", "NER": "O"}}}, "20": {"20": {"token_id": "20", "token": {"word": "she", "lemma": "she", "POS": "PRP", "NER": "O"}}}, "21": {"28": {"token_id": "28", "token": {"word": "her", "lemma": "she", "POS": "PRP$", "NER": "O"}}}, "23": {"25": {"token_id": "25", "token": {"word": "her", "lemma": "she", "POS": "PRP$", "NER": "O"}}}, "24": {"47": {"token_id": "47", "token": {"word": "her", "lemma": "she", "POS": "PRP$", "NER": "O"}}}, "25": {"14": {"token_id": "14", "token": {"word": "she", "lemma": "she", "POS": "PRP", "NER": "O"}}}, "26": {"20": {"token_id": "20", "token": {"word": "grandmother", "lemma": "grandmother", "POS": "NN", "NER": "O"}}}, "27": {"17": {"token_id": "17", "token": {"word": "she", "lemma": "she", "POS": "PRP", "NER": "O"}}}, "29": {"17": {"token_id": "17", "token": {"word": "her", "lemma": "she", "POS": "PRP$", "NER": "O"}}}, "30": {"32": {"token_id": "32", "token": {"word": "women", "lemma": "woman", "POS": "NNS", "NER": "O"}}}, "31": {"30": {"token_id": "30", "token": {"word": "she", "lemma": "she", "POS": "PRP", "NER": "O"}}}, "32": {"3": {"token_id": "3", "token": {"word": "women", "lemma": "woman", "POS": "NNS", "NER": "O"}}}, "33": {"72": {"token_id": "72", "token": {"word": "her", "lemma": "she", "POS": "PRP$", "NER": "O"}}}, "34": {"11": {"token_id": "11", "token": {"word": "women", "lemma": "woman", "POS": "NNS", "NER": "O"}}}}, {"39": {"17": {"token_id": "17", "token": {"word": "she", "lemma": "she", "POS": "PRP", "NER": "O"}}}, "40": {"4": {"token_id": "4", "token": {"word": "she", "lemma": "she", "POS": "PRP", "NER": "O"}}}, "41": {"1": {"token_id": "1", "token": {"word": "She", "lemma": "she", "POS": "PRP", "NER": "O"}}}, "42": {"1": {"token_id": "1", "token": {"word": "She", "lemma": "she", "POS": "PRP", "NER": "O"}}}, "43": {"9": {"token_id": "9", "token": {"word": "her", "lemma": "she", "POS": "PRP$", "NER": "O"}}}, "74": {"34": {"token_id": "34", "token": {"word": "she", "lemma": "she", "POS": "PRP", "NER": "O"}}}, "77": {"1": {"token_id": "1", "token": {"word": "She", "lemma": "she", "POS": "PRP", "NER": "O"}}}, "78": {"1": {"token_id": "1", "token": {"word": "She", "lemma": "she", "POS": "PRP", "NER": "O"}}}, "79": {"22": {"token_id": "22", "token": {"word": "her", "lemma": "she", "POS": "PRP$", "NER": "O"}}}, "80": {"11": {"token_id": "11", "token": {"word": "her", "lemma": "she", "POS": "PRP", "NER": "O"}}}}, {"8": {"12": {"token_id": "12", "token": {"word": "her", "lemma": "she", "POS": "PRP$", "NER": "O"}}}, "11": {"14": {"token_id": "14", "token": {"word": "her", "lemma": "she", "POS": "PRP$", "NER": "O"}}}, "13": {"3": {"token_id": "3", "token": {"word": "her", "lemma": "she", "POS": "PRP$", "NER": "O"}}}, "16": {"5": {"token_id": "5", "token": {"word": "her", "lemma": "she", "POS": "PRP$", "NER": "O"}}}, "17": {"1": {"token_id": "1", "token": {"word": "She", "lemma": "she", "POS": "PRP", "NER": "O"}}}, "20": {"19": {"token_id": "19", "token": {"word": "her", "lemma": "she", "POS": "PRP$", "NER": "O"}}}, "21": {"9": {"token_id": "9", "token": {"word": "she", "lemma": "she", "POS": "PRP", "NER": "O"}}}, "23": {"10": {"token_id": "10", "token": {"word": "her", "lemma": "she", "POS": "PRP$", "NER": "O"}}}, "24": {"12": {"token_id": "12", "token": {"word": "her", "lemma": "she", "POS": "PRP$", "NER": "O"}}}, "27": {"15": {"token_id": "15", "token": {"word": "her", "lemma": "she", "POS": "PRP", "NER": "O"}}}, "29": {"18": {"token_id": "18", "token": {"word": "her", "lemma": "she", "POS": "PRP$", "NER": "O"}}}, "30": {"37": {"token_id": "37", "token": {"word": "her", "lemma": "she", "POS": "PRP$", "NER": "O"}}}, "32": {"6": {"token_id": "6", "token": {"word": "her", "lemma": "she", "POS": "PRP$", "NER": "O"}}}, "34": {"4": {"token_id": "4", "token": {"word": "she", "lemma": "she", "POS": "PRP", "NER": "O"}}}}, {"8": {"17": {"token_id": "17", "token": {"word": "woman", "lemma": "woman", "POS": "NN", "NER": "O"}}}, "10": {"9": {"token_id": "9", "token": {"word": "queen", "lemma": "queen", "POS": "NN", "NER": "O"}}}, "11": {"15": {"token_id": "15", "token": {"word": "women", "lemma": "woman", "POS": "NNS", "NER": "O"}}}, "15": {"9": {"token_id": "9", "token": {"word": "girlfriend", "lemma": "girlfriend", "POS": "NN", "NER": "O"}}}}, {"1": {"17": {"token_id": "17", "token": {"word": "wife", "lemma": "wife", "POS": "NN", "NER": "O"}}}, "2": {"18": {"token_id": "18", "token": {"word": "her", "lemma": "she", "POS": "PRP$", "NER": "O"}}}, "3": {"18": {"token_id": "18", "token": {"word": "wife", "lemma": "wife", "POS": "NN", "NER": "O"}}}, "6": {"23": {"token_id": "23", "token": {"word": "lady", "lemma": "lady", "POS": "NN", "NER": "O"}}}}, {"15": {"19": {"token_id": "19", "token": {"word": "her", "lemma": "she", "POS": "PRP$", "NER": "O"}}}, "24": {"22": {"token_id": "22", "token": {"word": "her", "lemma": "she", "POS": "PRP$", "NER": "O"}}}}, {"11": {"18": {"token_id": "18", "token": {"word": "women", "lemma": "woman", "POS": "NNS", "NER": "O"}}}, "19": {"22": {"token_id": "22", "token": {"word": "she", "lemma": "she", "POS": "PRP", "NER": "O"}}}, "21": {"16": {"token_id": "16", "token": {"word": "girlfriend", "lemma": "girlfriend", "POS": "NN", "NER": "O"}}}}, {"2": {"15": {"token_id": "15", "token": {"word": "daughter", "lemma": "daughter", "POS": "NN", "NER": "O"}}}, "4": {"15": {"token_id": "15", "token": {"word": "her", "lemma": "she", "POS": "PRP$", "NER": "O"}}}, "5": {"13": {"token_id": "13", "token": {"word": "her", "lemma": "she", "POS": "PRP$", "NER": "O"}}}, "15": {"17": {"token_id": "17", "token": {"word": "daughter", "lemma": "daughter", "POS": "NN", "NER": "O"}}}, "17": {"8": {"token_id": "8", "token": {"word": "mother", "lemma": "mother", "POS": "NN", "NER": "O"}}}, "20": {"10": {"token_id": "10", "token": {"word": "queen", "lemma": "queen", "POS": "NN", "NER": "O"}}}, "21": {"18": {"token_id": "18", "token": {"word": "her", "lemma": "she", "POS": "PRP", "NER": "O"}}}, "24": {"26": {"token_id": "26", "token": {"word": "her", "lemma": "she", "POS": "PRP$", "NER": "O"}}}, "28": {"31": {"token_id": "31", "token": {"word": "her", "lemma": "she", "POS": "PRP$", "NER": "O"}}}, "29": {"30": {"token_id": "30", "token": {"word": "she", "lemma": "she", "POS": "PRP", "NER": "O"}}}, "30": {"32": {"token_id": "32", "token": {"word": "her", "lemma": "she", "POS": "PRP$", "NER": "O"}}}, "33": {"7": {"token_id": "7", "token": {"word": "she", "lemma": "she", "POS": "PRP", "NER": "O"}}}, "37": {"20": {"token_id": "20", "token": {"word": "her", "lemma": "she", "POS": "PRP", "NER": "O"}}}, "38": {"20": {"token_id": "20", "token": {"word": "she", "lemma": "she", "POS": "PRP", "NER": "O"}}}, "40": {"9": {"token_id": "9", "token": {"word": "her", "lemma": "she", "POS": "PRP$", "NER": "O"}}}, "41": {"22": {"token_id": "22", "token": {"word": "her", "lemma": "she", "POS": "PRP$", "NER": "O"}}}, "43": {"14": {"token_id": "14", "token": {"word": "her", "lemma": "she", "POS": "PRP", "NER": "O"}}}, "44": {"20": {"token_id": "20", "token": {"word": "her", "lemma": "she", "POS": "PRP$", "NER": "O"}}}, "45": {"18": {"token_id": "18", "token": {"word": "her", "lemma": "she", "POS": "PRP$", "NER": "O"}}}, "48": {"22": {"token_id": "22", "token": {"word": "mother", "lemma": "mother", "POS": "NN", "NER": "O"}}}, "56": {"16": {"token_id": "16", "token": {"word": "daughter", "lemma": "daughter", "POS": "NN", "NER": "O"}}}, "58": {"18": {"token_id": "18", "token": {"word": "she", "lemma": "she", "POS": "PRP", "NER": "O"}}}, "59": {"5": {"token_id": "5", "token": {"word": "her", "lemma": "she", "POS": "PRP$", "NER": "O"}}}, "60": {"21": {"token_id": "21", "token": {"word": "she", "lemma": "she", "POS": "PRP", "NER": "O"}}}, "61": {"11": {"token_id": "11", "token": {"word": "her", "lemma": "she", "POS": "PRP$", "NER": "O"}}}, "65": {"15": {"token_id": "15", "token": {"word": "she", "lemma": "she", "POS": "PRP", "NER": "O"}}}, "67": {"19": {"token_id": "19", "token": {"word": "she", "lemma": "she", "POS": "PRP", "NER": "O"}}}, "72": {"27": {"token_id": "27", "token": {"word": "her", "lemma": "she", "POS": "PRP$", "NER": "O"}}}}, {"2": {"9": {"token_id": "9", "token": {"word": "female", "lemma": "female", "POS": "JJ", "NER": "O"}}}, "3": {"1": {"token_id": "1", "token": {"word": "She", "lemma": "she", "POS": "PRP", "NER": "O"}}}, "4": {"7": {"token_id": "7", "token": {"word": "her", "lemma": "she", "POS": "PRP$", "NER": "O"}}}, "5": {"6": {"token_id": "6", "token": {"word": "her", "lemma": "she", "POS": "PRP", "NER": "O"}}}, "8": {"13": {"token_id": "13", "token": {"word": "her", "lemma": "she", "POS": "PRP", "NER": "O"}}}, "10": {"4": {"token_id": "4", "token": {"word": "she", "lemma": "she", "POS": "PRP", "NER": "O"}}}, "11": {"17": {"token_id": "17", "token": {"word": "girl", "lemma": "girl", "POS": "NN", "NER": "O"}}}, "12": {"22": {"token_id": "22", "token": {"word": "her", "lemma": "she", "POS": "PRP$", "NER": "O"}}}, "13": {"6": {"token_id": "6", "token": {"word": "her", "lemma": "she", "POS": "PRP$", "NER": "O"}}}, "14": {"1": {"token_id": "1", "token": {"word": "She", "lemma": "she", "POS": "PRP", "NER": "O"}}}, "15": {"6": {"token_id": "6", "token": {"word": "her", "lemma": "she", "POS": "PRP$", "NER": "O"}}}, "16": {"14": {"token_id": "14", "token": {"word": "her", "lemma": "she", "POS": "PRP", "NER": "O"}}}, "17": {"3": {"token_id": "3", "token": {"word": "her", "lemma": "she", "POS": "PRP$", "NER": "O"}}}, "21": {"5": {"token_id": "5", "token": {"word": "she", "lemma": "she", "POS": "PRP", "NER": "O"}}}, "23": {"13": {"token_id": "13", "token": {"word": "her", "lemma": "she", "POS": "PRP$", "NER": "O"}}}, "25": {"10": {"token_id": "10", "token": {"word": "her", "lemma": "she", "POS": "PRP", "NER": "O"}}}, "26": {"7": {"token_id": "7", "token": {"word": "her", "lemma": "she", "POS": "PRP$", "NER": "O"}}}, "27": {"1": {"token_id": "1", "token": {"word": "Her", "lemma": "she", "POS": "PRP$", "NER": "O"}}}, "29": {"11": {"token_id": "11", "token": {"word": "her", "lemma": "she", "POS": "PRP$", "NER": "O"}}}, "30": {"9": {"token_id": "9", "token": {"word": "she", "lemma": "she", "POS": "PRP", "NER": "O"}}}, "31": {"15": {"token_id": "15", "token": {"word": "she", "lemma": "she", "POS": "PRP", "NER": "O"}}}, "32": {"4": {"token_id": "4", "token": {"word": "her", "lemma": "she", "POS": "PRP", "NER": "O"}}}, "33": {"8": {"token_id": "8", "token": {"word": "she", "lemma": "she", "POS": "PRP", "NER": "O"}}}, "34": {"10": {"token_id": "10", "token": {"word": "her", "lemma": "she", "POS": "PRP$", "NER": "O"}}}, "36": {"14": {"token_id": "14", "token": {"word": "she", "lemma": "she", "POS": "PRP", "NER": "O"}}}, "37": {"19": {"token_id": "19", "token": {"word": "her", "lemma": "she", "POS": "PRP$", "NER": "O"}}}, "38": {"4": {"token_id": "4", "token": {"word": "her", "lemma": "she", "POS": "PRP", "NER": "O"}}}, "39": {"23": {"token_id": "23", "token": {"word": "she", "lemma": "she", "POS": "PRP", "NER": "O"}}}, "40": {"23": {"token_id": "23", "token": {"word": "she", "lemma": "she", "POS": "PRP", "NER": "O"}}}, "41": {"12": {"token_id": "12", "token": {"word": "her", "lemma": "she", "POS": "PRP$", "NER": "O"}}}, "42": {"4": {"token_id": "4", "token": {"word": "she", "lemma": "she", "POS": "PRP", "NER": "O"}}}, "44": {"3": {"token_id": "3", "token": {"word": "her", "lemma": "she", "POS": "PRP$", "NER": "O"}}}, "45": {"16": {"token_id": "16", "token": {"word": "missed", "lemma": "miss", "POS": "VBN", "NER": "O"}}}, "46": {"1": {"token_id": "1", "token": {"word": "She", "lemma": "she", "POS": "PRP", "NER": "O"}}}, "50": {"20": {"token_id": "20", "token": {"word": "her", "lemma": "she", "POS": "PRP", "NER": "O"}}}, "51": {"15": {"token_id": "15", "token": {"word": "her", "lemma": "she", "POS": "PRP", "NER": "O"}}}, "52": {"17": {"token_id": "17", "token": {"word": "her", "lemma": "she", "POS": "PRP$", "NER": "O"}}}, "53": {"25": {"token_id": "25", "token": {"word": "her", "lemma": "she", "POS": "PRP", "NER": "O"}}}, "55": {"16": {"token_id": "16", "token": {"word": "her", "lemma": "she", "POS": "PRP$", "NER": "O"}}}, "58": {"7": {"token_id": "7", "token": {"word": "her", "lemma": "she", "POS": "PRP$", "NER": "O"}}}, "59": {"9": {"token_id": "9", "token": {"word": "she", "lemma": "she", "POS": "PRP", "NER": "O"}}}, "61": {"14": {"token_id": "14", "token": {"word": "her", "lemma": "she", "POS": "PRP$", "NER": "O"}}}, "62": {"8": {"token_id": "8", "token": {"word": "her", "lemma": "she", "POS": "PRP$", "NER": "O"}}}, "63": {"9": {"token_id": "9", "token": {"word": "she", "lemma": "she", "POS": "PRP", "NER": "O"}}}, "66": {"16": {"token_id": "16", "token": {"word": "wife", "lemma": "wife", "POS": "NN", "NER": "O"}}}, "70": {"5": {"token_id": "5", "token": {"word": "her", "lemma": "she", "POS": "PRP$", "NER": "O"}}}, "72": {"16": {"token_id": "16", "token": {"word": "her", "lemma": "she", "POS": "PRP$", "NER": "O"}}}, "74": {"12": {"token_id": "12", "token": {"word": "her", "lemma": "she", "POS": "PRP", "NER": "O"}}}, "75": {"11": {"token_id": "11", "token": {"word": "she", "lemma": "she", "POS": "PRP", "NER": "O"}}}, "78": {"16": {"token_id": "16", "token": {"word": "her", "lemma": "she", "POS": "PRP$", "NER": "O"}}}, "80": {"1": {"token_id": "1", "token": {"word": "She", "lemma": "she", "POS": "PRP", "NER": "O"}}}, "88": {"5": {"token_id": "5", "token": {"word": "her", "lemma": "she", "POS": "PRP$", "NER": "O"}}}, "90": {"5": {"token_id": "5", "token": {"word": "she", "lemma": "she", "POS": "PRP", "NER": "O"}}}, "92": {"4": {"token_id": "4", "token": {"word": "her", "lemma": "she", "POS": "PRP$", "NER": "O"}}}, "93": {"6": {"token_id": "6", "token": {"word": "girl", "lemma": "girl", "POS": "NN", "NER": "O"}}}, "95": {"4": {"token_id": "4", "token": {"word": "she", "lemma": "she", "POS": "PRP", "NER": "O"}}}, "98": {"11": {"token_id": "11", "token": {"word": "her", "lemma": "she", "POS": "PRP$", "NER": "O"}}}, "101": {"15": {"token_id": "15", "token": {"word": "her", "lemma": "she", "POS": "PRP", "NER": "O"}}}, "104": {"16": {"token_id": "16", "token": {"word": "she", "lemma": "she", "POS": "PRP", "NER": "O"}}}, "106": {"18": {"token_id": "18", "token": {"word": "her", "lemma": "she", "POS": "PRP", "NER": "O"}}}, "108": {"9": {"token_id": "9", "token": {"word": "her", "lemma": "she", "POS": "PRP$", "NER": "O"}}}, "110": {"15": {"token_id": "15", "token": {"word": "wife", "lemma": "wife", "POS": "NN", "NER": "O"}}}, "113": {"20": {"token_id": "20", "token": {"word": "her", "lemma": "she", "POS": "PRP$", "NER": "O"}}}, "114": {"8": {"token_id": "8", "token": {"word": "she", "lemma": "she", "POS": "PRP", "NER": "O"}}}, "115": {"6": {"token_id": "6", "token": {"word": "she", "lemma": "she", "POS": "PRP", "NER": "O"}}}, "118": {"9": {"token_id": "9", "token": {"word": "her", "lemma": "she", "POS": "PRP$", "NER": "O"}}}, "120": {"1": {"token_id": "1", "token": {"word": "She", "lemma": "she", "POS": "PRP", "NER": "O"}}}, "122": {"12": {"token_id": "12", "token": {"word": "she", "lemma": "she", "POS": "PRP", "NER": "O"}}}, "123": {"12": {"token_id": "12", "token": {"word": "her", "lemma": "she", "POS": "PRP$", "NER": "O"}}}, "124": {"14": {"token_id": "14", "token": {"word": "her", "lemma": "she", "POS": "PRP", "NER": "O"}}}, "125": {"5": {"token_id": "5", "token": {"word": "girl", "lemma": "girl", "POS": "NN", "NER": "O"}}}, "126": {"11": {"token_id": "11", "token": {"word": "girl", "lemma": "girl", "POS": "NN", "NER": "O"}}}, "128": {"8": {"token_id": "8", "token": {"word": "she", "lemma": "she", "POS": "PRP", "NER": "O"}}}, "130": {"18": {"token_id": "18", "token": {"word": "her", "lemma": "she", "POS": "PRP", "NER": "O"}}}, "131": {"14": {"token_id": "14", "token": {"word": "her", "lemma": "she", "POS": "PRP", "NER": "O"}}}, "132": {"12": {"token_id": "12", "token": {"word": "her", "lemma": "she", "POS": "PRP$", "NER": "O"}}}, "133": {"29": {"token_id": "29", "token": {"word": "her", "lemma": "she", "POS": "PRP$", "NER": "O"}}}, "134": {"10": {"token_id": "10", "token": {"word": "wife", "lemma": "wife", "POS": "NN", "NER": "O"}}}, "135": {"4": {"token_id": "4", "token": {"word": "she", "lemma": "she", "POS": "PRP", "NER": "O"}}}, "136": {"17": {"token_id": "17", "token": {"word": "daughters", "lemma": "daughter", "POS": "NNS", "NER": "O"}}}, "139": {"11": {"token_id": "11", "token": {"word": "daughters", "lemma": "daughter", "POS": "NNS", "NER": "O"}}}, "140": {"10": {"token_id": "10", "token": {"word": "her", "lemma": "she", "POS": "PRP$", "NER": "O"}}}}, {"5": {"42": {"token_id": "42", "token": {"word": "her", "lemma": "she", "POS": "PRP$", "NER": "O"}}}, "6": {"7": {"token_id": "7", "token": {"word": "her", "lemma": "she", "POS": "PRP$", "NER": "O"}}}, "7": {"12": {"token_id": "12", "token": {"word": "she", "lemma": "she", "POS": "PRP", "NER": "O"}}}, "9": {"18": {"token_id": "18", "token": {"word": "women", "lemma": "woman", "POS": "NNS", "NER": "O"}}}}, {"5": {"16": {"token_id": "16", "token": {"word": "feminine", "lemma": "feminine", "POS": "JJ", "NER": "O"}}}}, {"4": {"33": {"token_id": "33", "token": {"word": "mother", "lemma": "mother", "POS": "NN", "NER": "O"}}}, "5": {"15": {"token_id": "15", "token": {"word": "her", "lemma": "she", "POS": "PRP", "NER": "O"}}}, "6": {"4": {"token_id": "4", "token": {"word": "her", "lemma": "she", "POS": "PRP", "NER": "O"}}}, "7": {"14": {"token_id": "14", "token": {"word": "her", "lemma": "she", "POS": "PRP$", "NER": "O"}}}, "8": {"14": {"token_id": "14", "token": {"word": "she", "lemma": "she", "POS": "PRP", "NER": "O"}}}, "9": {"24": {"token_id": "24", "token": {"word": "her", "lemma": "she", "POS": "PRP", "NER": "O"}}}, "10": {"13": {"token_id": "13", "token": {"word": "her", "lemma": "she", "POS": "PRP", "NER": "O"}}}, "11": {"14": {"token_id": "14", "token": {"word": "her", "lemma": "she", "POS": "PRP$", "NER": "O"}}}, "12": {"13": {"token_id": "13", "token": {"word": "her", "lemma": "she", "POS": "PRP", "NER": "O"}}}, "13": {"21": {"token_id": "21", "token": {"word": "she", "lemma": "she", "POS": "PRP", "NER": "O"}}}, "15": {"5": {"token_id": "5", "token": {"word": "her", "lemma": "she", "POS": "PRP", "NER": "O"}}}, "16": {"5": {"token_id": "5", "token": {"word": "she", "lemma": "she", "POS": "PRP", "NER": "O"}}}, "17": {"32": {"token_id": "32", "token": {"word": "wife", "lemma": "wife", "POS": "NN", "NER": "O"}}}, "19": {"7": {"token_id": "7", "token": {"word": "her", "lemma": "she", "POS": "PRP$", "NER": "O"}}}}]